[{"id":"askl021_2026-06-25_최재성_T_네오_실피드_20.7_단판_스페이드리그_1경기","date":"2026-06-25","standardDate":"2026-06-25","playedAt":"2026-06-25","playerName":"빡죠스","playerRace":"P","playerUserId":"askl021","opponentName":"최재성","opponentRace":"T","map":"네오 실피드","elo":20.7,"eloChange":20.7,"matchType":"단판","memo":"스페이드리그 1경기","result":"win","isWin":true,"winnerPlayer":"빡죠스","winnerName":"빡죠스","winnerRace":"P","losePlayer":"최재성","loseName":"최재성","loseRace":"T","winnerSoopUserId":"askl021","winnerUserId":"askl021","loseSoopUserId":"","loserSoopUserId":"","loseUserId":"","loserUserId":""},{"id":"askl021_2026-06-05_박태민_Z_폴리포이드_18.5_9/5(6)_엠비대_읍_CK(6)","date":"2026-06-05","standardDate":"2026-06-05","playedAt":"2026-06-05","playerName":"빡죠스","playerRace":"P","playerUserId":"askl021","opponentName":"박태민","opponentRace":"Z","map":"폴리포이드","elo":18.5,"eloChange":18.5,"matchType":"9/5(6)","memo":"엠비대 읍 CK(6)","result":"win","isWin":true,"winnerPlayer":"빡죠스","winnerName":"빡죠스","winnerRace":"P","losePlayer":"박태민","loseName":"박태민","loseRace":"Z","winnerSoopUserId":"askl021","winnerUserId":"askl021","loseSoopUserId":"","loserSoopUserId":"","loseUserId":"","loserUserId":""},{"id":"askl021_2026-06-05_박태민_Z_녹아웃_-14.9_9/5(2)_엠비대_읍_CK(2)","date":"2026-06-05","standardDate":"2026-06-05","playedAt":"2026-06-05","playerName":"빡죠스","playerRace":"P","playerUserId":"askl021","opponentName":"박태민","opponentRace":"Z","map":"녹아웃","elo":-14.9,"eloChange":-14.9,"matchType":"9/5(2)","memo":"엠비대 읍 CK(2)","result":"lose","isWin":false,"winnerPlayer":"박태민","winnerName":"박태민","winnerRace":"Z","losePlayer":"빡죠스","loseName":"빡죠스","loseRace":"P","winnerSoopUserId":"","winnerUserId":"","loseSoopUserId":"askl021","loserSoopUserId":"askl021","loseUserId":"askl021","loserUserId":"askl021"},{"id":"askl021_2026-05-23_박성준_Z_라데온_-14.3_9/5(3)_소룡CK_(3)","date":"2026-05-23","standardDate":"2026-05-23","playedAt":"2026-05-23","playerName":"빡죠스","playerRace":"P","playerUserId":"askl021","opponentName":"박성준","opponentRace":"Z","map":"라데온","elo":-14.3,"eloChange":-14.3,"matchType":"9/5(3)","memo":"소룡CK (3)","result":"lose","isWin":false,"winnerPlayer":"박성준","winnerName":"박성준","winnerRace":"Z","losePlayer":"빡죠스","loseName":"빡죠스","loseRace":"P","winnerSoopUserId":"","winnerUserId":"","loseSoopUserId":"askl021","loserSoopUserId":"askl021","loseUserId":"askl021","loserUserId":"askl021"}]