[{"id":"chs9011_2026-04-22_슬돌이_P_라데온_10.2_3/2(3)_3/2","date":"2026-04-22","standardDate":"2026-04-22","playedAt":"2026-04-22","playerName":"모토케이","playerRace":"T","playerUserId":"chs9011","opponentName":"슬돌이","opponentRace":"P","map":"라데온","elo":10.2,"eloChange":10.2,"matchType":"3/2(3)","memo":"3/2","result":"win","isWin":true,"winnerPlayer":"모토케이","winnerName":"모토케이","winnerRace":"T","losePlayer":"슬돌이","loseName":"슬돌이","loseRace":"P","winnerSoopUserId":"chs9011","winnerUserId":"chs9011","loseSoopUserId":"","loserSoopUserId":"","loseUserId":"","loserUserId":""},{"id":"chs9011_2026-04-22_슬돌이_P_네오실피드_11.1_3/2(2)_3/2","date":"2026-04-22","standardDate":"2026-04-22","playedAt":"2026-04-22","playerName":"모토케이","playerRace":"T","playerUserId":"chs9011","opponentName":"슬돌이","opponentRace":"P","map":"네오실피드","elo":11.1,"eloChange":11.1,"matchType":"3/2(2)","memo":"3/2","result":"win","isWin":true,"winnerPlayer":"모토케이","winnerName":"모토케이","winnerRace":"T","losePlayer":"슬돌이","loseName":"슬돌이","loseRace":"P","winnerSoopUserId":"chs9011","winnerUserId":"chs9011","loseSoopUserId":"","loserSoopUserId":"","loseUserId":"","loserUserId":""},{"id":"chs9011_2026-04-22_슬돌이_P_폴리포이드_-22.7_3/2(1)_3/2","date":"2026-04-22","standardDate":"2026-04-22","playedAt":"2026-04-22","playerName":"모토케이","playerRace":"T","playerUserId":"chs9011","opponentName":"슬돌이","opponentRace":"P","map":"폴리포이드","elo":-22.7,"eloChange":-22.7,"matchType":"3/2(1)","memo":"3/2","result":"lose","isWin":false,"winnerPlayer":"슬돌이","winnerName":"슬돌이","winnerRace":"P","losePlayer":"모토케이","loseName":"모토케이","loseRace":"T","winnerSoopUserId":"","winnerUserId":"","loseSoopUserId":"chs9011","loserSoopUserId":"chs9011","loseUserId":"chs9011","loserUserId":"chs9011"},{"id":"chs9011_2026-04-21_다나짱_P_녹아웃_-22.6_단판_단판_3판(3)","date":"2026-04-21","standardDate":"2026-04-21","playedAt":"2026-04-21","playerName":"모토케이","playerRace":"T","playerUserId":"chs9011","opponentName":"다나짱","opponentRace":"P","map":"녹아웃","elo":-22.6,"eloChange":-22.6,"matchType":"단판","memo":"단판 3판(3)","result":"lose","isWin":false,"winnerPlayer":"다나짱","winnerName":"다나짱","winnerRace":"P","losePlayer":"모토케이","loseName":"모토케이","loseRace":"T","winnerSoopUserId":"","winnerUserId":"","loseSoopUserId":"chs9011","loserSoopUserId":"chs9011","loseUserId":"chs9011","loserUserId":"chs9011"},{"id":"chs9011_2026-04-21_다나짱_P_라데온_10.1_단판_단판_3판(2)","date":"2026-04-21","standardDate":"2026-04-21","playedAt":"2026-04-21","playerName":"모토케이","playerRace":"T","playerUserId":"chs9011","opponentName":"다나짱","opponentRace":"P","map":"라데온","elo":10.1,"eloChange":10.1,"matchType":"단판","memo":"단판 3판(2)","result":"win","isWin":true,"winnerPlayer":"모토케이","winnerName":"모토케이","winnerRace":"T","losePlayer":"다나짱","loseName":"다나짱","loseRace":"P","winnerSoopUserId":"chs9011","winnerUserId":"chs9011","loseSoopUserId":"","loserSoopUserId":"","loseUserId":"","loserUserId":""},{"id":"chs9011_2026-04-21_다나짱_P_폴리포이드_-23.6_단판_단판_3판(1)","date":"2026-04-21","standardDate":"2026-04-21","playedAt":"2026-04-21","playerName":"모토케이","playerRace":"T","playerUserId":"chs9011","opponentName":"다나짱","opponentRace":"P","map":"폴리포이드","elo":-23.6,"eloChange":-23.6,"matchType":"단판","memo":"단판 3판(1)","result":"lose","isWin":false,"winnerPlayer":"다나짱","winnerName":"다나짱","winnerRace":"P","losePlayer":"모토케이","loseName":"모토케이","loseRace":"T","winnerSoopUserId":"","winnerUserId":"","loseSoopUserId":"chs9011","loserSoopUserId":"chs9011","loseUserId":"chs9011","loserUserId":"chs9011"},{"id":"chs9011_2026-04-19_다나짱_P_녹아웃_-25.3_단판_단판_3판(3)","date":"2026-04-19","standardDate":"2026-04-19","playedAt":"2026-04-19","playerName":"모토케이","playerRace":"T","playerUserId":"chs9011","opponentName":"다나짱","opponentRace":"P","map":"녹아웃","elo":-25.3,"eloChange":-25.3,"matchType":"단판","memo":"단판 3판(3)","result":"lose","isWin":false,"winnerPlayer":"다나짱","winnerName":"다나짱","winnerRace":"P","losePlayer":"모토케이","loseName":"모토케이","loseRace":"T","winnerSoopUserId":"","winnerUserId":"","loseSoopUserId":"chs9011","loserSoopUserId":"chs9011","loseUserId":"chs9011","loserUserId":"chs9011"},{"id":"chs9011_2026-04-19_다나짱_P_라데온_7.1_단판_단판_3판(2)","date":"2026-04-19","standardDate":"2026-04-19","playedAt":"2026-04-19","playerName":"모토케이","playerRace":"T","playerUserId":"chs9011","opponentName":"다나짱","opponentRace":"P","map":"라데온","elo":7.1,"eloChange":7.1,"matchType":"단판","memo":"단판 3판(2)","result":"win","isWin":true,"winnerPlayer":"모토케이","winnerName":"모토케이","winnerRace":"T","losePlayer":"다나짱","loseName":"다나짱","loseRace":"P","winnerSoopUserId":"chs9011","winnerUserId":"chs9011","loseSoopUserId":"","loserSoopUserId":"","loseUserId":"","loserUserId":""},{"id":"chs9011_2026-04-19_다나짱_P_폴리포이드_7.6_단판_단판_3판(1)","date":"2026-04-19","standardDate":"2026-04-19","playedAt":"2026-04-19","playerName":"모토케이","playerRace":"T","playerUserId":"chs9011","opponentName":"다나짱","opponentRace":"P","map":"폴리포이드","elo":7.6,"eloChange":7.6,"matchType":"단판","memo":"단판 3판(1)","result":"win","isWin":true,"winnerPlayer":"모토케이","winnerName":"모토케이","winnerRace":"T","losePlayer":"다나짱","loseName":"다나짱","loseRace":"P","winnerSoopUserId":"chs9011","winnerUserId":"chs9011","loseSoopUserId":"","loserSoopUserId":"","loseUserId":"","loserUserId":""},{"id":"chs9011_2024-09-16_다나짱_P_폴리포이드_6.9_단판_단판","date":"2024-09-16","standardDate":"2024-09-16","playedAt":"2024-09-16","playerName":"모토케이","playerRace":"T","playerUserId":"chs9011","opponentName":"다나짱","opponentRace":"P","map":"폴리포이드","elo":6.9,"eloChange":6.9,"matchType":"단판","memo":"단판","result":"win","isWin":true,"winnerPlayer":"모토케이","winnerName":"모토케이","winnerRace":"T","losePlayer":"다나짱","loseName":"다나짱","loseRace":"P","winnerSoopUserId":"chs9011","winnerUserId":"chs9011","loseSoopUserId":"","loserSoopUserId":"","loseUserId":"","loserUserId":""},{"id":"chs9011_2024-09-16_다나짱_P_폴리포이드_7.3_단판_단판","date":"2024-09-16","standardDate":"2024-09-16","playedAt":"2024-09-16","playerName":"모토케이","playerRace":"T","playerUserId":"chs9011","opponentName":"다나짱","opponentRace":"P","map":"폴리포이드","elo":7.3,"eloChange":7.3,"matchType":"단판","memo":"단판","result":"win","isWin":true,"winnerPlayer":"모토케이","winnerName":"모토케이","winnerRace":"T","losePlayer":"다나짱","loseName":"다나짱","loseRace":"P","winnerSoopUserId":"chs9011","winnerUserId":"chs9011","loseSoopUserId":"","loserSoopUserId":"","loseUserId":"","loserUserId":""},{"id":"chs9011_2024-09-16_다나짱_P_폴리포이드_7.9_단판_단판","date":"2024-09-16","standardDate":"2024-09-16","playedAt":"2024-09-16","playerName":"모토케이","playerRace":"T","playerUserId":"chs9011","opponentName":"다나짱","opponentRace":"P","map":"폴리포이드","elo":7.9,"eloChange":7.9,"matchType":"단판","memo":"단판","result":"win","isWin":true,"winnerPlayer":"모토케이","winnerName":"모토케이","winnerRace":"T","losePlayer":"다나짱","loseName":"다나짱","loseRace":"P","winnerSoopUserId":"chs9011","winnerUserId":"chs9011","loseSoopUserId":"","loserSoopUserId":"","loseUserId":"","loserUserId":""},{"id":"chs9011_2024-09-16_다나짱_P_버미어_8.4_단판_단판","date":"2024-09-16","standardDate":"2024-09-16","playedAt":"2024-09-16","playerName":"모토케이","playerRace":"T","playerUserId":"chs9011","opponentName":"다나짱","opponentRace":"P","map":"버미어","elo":8.4,"eloChange":8.4,"matchType":"단판","memo":"단판","result":"win","isWin":true,"winnerPlayer":"모토케이","winnerName":"모토케이","winnerRace":"T","losePlayer":"다나짱","loseName":"다나짱","loseRace":"P","winnerSoopUserId":"chs9011","winnerUserId":"chs9011","loseSoopUserId":"","loserSoopUserId":"","loseUserId":"","loserUserId":""},{"id":"chs9011_2024-09-16_다나짱_P_폴리포이드_9.1_단판_단판","date":"2024-09-16","standardDate":"2024-09-16","playedAt":"2024-09-16","playerName":"모토케이","playerRace":"T","playerUserId":"chs9011","opponentName":"다나짱","opponentRace":"P","map":"폴리포이드","elo":9.1,"eloChange":9.1,"matchType":"단판","memo":"단판","result":"win","isWin":true,"winnerPlayer":"모토케이","winnerName":"모토케이","winnerRace":"T","losePlayer":"다나짱","loseName":"다나짱","loseRace":"P","winnerSoopUserId":"chs9011","winnerUserId":"chs9011","loseSoopUserId":"","loserSoopUserId":"","loseUserId":"","loserUserId":""},{"id":"chs9011_2024-08-13_토스봇_P_폴리포이드_-17.1_단판_단판","date":"2024-08-13","standardDate":"2024-08-13","playedAt":"2024-08-13","playerName":"모토케이","playerRace":"T","playerUserId":"chs9011","opponentName":"토스봇","opponentRace":"P","map":"폴리포이드","elo":-17.1,"eloChange":-17.1,"matchType":"단판","memo":"단판","result":"lose","isWin":false,"winnerPlayer":"토스봇","winnerName":"토스봇","winnerRace":"P","losePlayer":"모토케이","loseName":"모토케이","loseRace":"T","winnerSoopUserId":"","winnerUserId":"","loseSoopUserId":"chs9011","loserSoopUserId":"chs9011","loseUserId":"chs9011","loserUserId":"chs9011"},{"id":"chs9011_2024-07-09_파메_P_버미어_14.3_단판_1","date":"2024-07-09","standardDate":"2024-07-09","playedAt":"2024-07-09","playerName":"모토케이","playerRace":"T","playerUserId":"chs9011","opponentName":"파메","opponentRace":"P","map":"버미어","elo":14.3,"eloChange":14.3,"matchType":"단판","memo":"1","result":"win","isWin":true,"winnerPlayer":"모토케이","winnerName":"모토케이","winnerRace":"T","losePlayer":"파메","loseName":"파메","loseRace":"P","winnerSoopUserId":"chs9011","winnerUserId":"chs9011","loseSoopUserId":"","loserSoopUserId":"","loseUserId":"","loserUserId":""},{"id":"chs9011_2024-07-09_유성민_P_버미어_-10.2_단판_스폰","date":"2024-07-09","standardDate":"2024-07-09","playedAt":"2024-07-09","playerName":"모토케이","playerRace":"T","playerUserId":"chs9011","opponentName":"유성민","opponentRace":"P","map":"버미어","elo":-10.2,"eloChange":-10.2,"matchType":"단판","memo":"스폰","result":"lose","isWin":false,"winnerPlayer":"유성민","winnerName":"유성민","winnerRace":"P","losePlayer":"모토케이","loseName":"모토케이","loseRace":"T","winnerSoopUserId":"","winnerUserId":"","loseSoopUserId":"chs9011","loserSoopUserId":"chs9011","loseUserId":"chs9011","loserUserId":"chs9011"},{"id":"chs9011_2024-07-08_토스봇_P_버미어_16.9_단판_1","date":"2024-07-08","standardDate":"2024-07-08","playedAt":"2024-07-08","playerName":"모토케이","playerRace":"T","playerUserId":"chs9011","opponentName":"토스봇","opponentRace":"P","map":"버미어","elo":16.9,"eloChange":16.9,"matchType":"단판","memo":"1","result":"win","isWin":true,"winnerPlayer":"모토케이","winnerName":"모토케이","winnerRace":"T","losePlayer":"토스봇","loseName":"토스봇","loseRace":"P","winnerSoopUserId":"chs9011","winnerUserId":"chs9011","loseSoopUserId":"","loserSoopUserId":"","loseUserId":"","loserUserId":""},{"id":"chs9011_2024-07-04_트슈_P_폴리포이드_-8.8_단판_1","date":"2024-07-04","standardDate":"2024-07-04","playedAt":"2024-07-04","playerName":"모토케이","playerRace":"T","playerUserId":"chs9011","opponentName":"트슈","opponentRace":"P","map":"폴리포이드","elo":-8.8,"eloChange":-8.8,"matchType":"단판","memo":"1","result":"lose","isWin":false,"winnerPlayer":"트슈","winnerName":"트슈","winnerRace":"P","losePlayer":"모토케이","loseName":"모토케이","loseRace":"T","winnerSoopUserId":"","winnerUserId":"","loseSoopUserId":"chs9011","loserSoopUserId":"chs9011","loseUserId":"chs9011","loserUserId":"chs9011"},{"id":"chs9011_2024-07-04_토스봇_P_폴리포이드_18.1_단판_단판","date":"2024-07-04","standardDate":"2024-07-04","playedAt":"2024-07-04","playerName":"모토케이","playerRace":"T","playerUserId":"chs9011","opponentName":"토스봇","opponentRace":"P","map":"폴리포이드","elo":18.1,"eloChange":18.1,"matchType":"단판","memo":"단판","result":"win","isWin":true,"winnerPlayer":"모토케이","winnerName":"모토케이","winnerRace":"T","losePlayer":"토스봇","loseName":"토스봇","loseRace":"P","winnerSoopUserId":"chs9011","winnerUserId":"chs9011","loseSoopUserId":"","loserSoopUserId":"","loseUserId":"","loserUserId":""},{"id":"chs9011_2024-07-01_파메_P_폴리포이드_17_단판_1","date":"2024-07-01","standardDate":"2024-07-01","playedAt":"2024-07-01","playerName":"모토케이","playerRace":"T","playerUserId":"chs9011","opponentName":"파메","opponentRace":"P","map":"폴리포이드","elo":17,"eloChange":17,"matchType":"단판","memo":"1","result":"win","isWin":true,"winnerPlayer":"모토케이","winnerName":"모토케이","winnerRace":"T","losePlayer":"파메","loseName":"파메","loseRace":"P","winnerSoopUserId":"chs9011","winnerUserId":"chs9011","loseSoopUserId":"","loserSoopUserId":"","loseUserId":"","loserUserId":""},{"id":"chs9011_2024-06-30_수입뿌드_P_레트로_20.4_3/2(2)_2","date":"2024-06-30","standardDate":"2024-06-30","playedAt":"2024-06-30","playerName":"모토케이","playerRace":"T","playerUserId":"chs9011","opponentName":"수입뿌드","opponentRace":"P","map":"레트로","elo":20.4,"eloChange":20.4,"matchType":"3/2(2)","memo":"2","result":"win","isWin":true,"winnerPlayer":"모토케이","winnerName":"모토케이","winnerRace":"T","losePlayer":"수입뿌드","loseName":"수입뿌드","loseRace":"P","winnerSoopUserId":"chs9011","winnerUserId":"chs9011","loseSoopUserId":"","loserSoopUserId":"","loseUserId":"","loserUserId":""},{"id":"chs9011_2024-06-30_수입뿌드_P_폴리포이드_22.3_3/2(1)_1","date":"2024-06-30","standardDate":"2024-06-30","playedAt":"2024-06-30","playerName":"모토케이","playerRace":"T","playerUserId":"chs9011","opponentName":"수입뿌드","opponentRace":"P","map":"폴리포이드","elo":22.3,"eloChange":22.3,"matchType":"3/2(1)","memo":"1","result":"win","isWin":true,"winnerPlayer":"모토케이","winnerName":"모토케이","winnerRace":"T","losePlayer":"수입뿌드","loseName":"수입뿌드","loseRace":"P","winnerSoopUserId":"chs9011","winnerUserId":"chs9011","loseSoopUserId":"","loserSoopUserId":"","loseUserId":"","loserUserId":""},{"id":"chs9011_2024-06-28_유성민_P_버미어_-11.8_3/2(2)_스폰","date":"2024-06-28","standardDate":"2024-06-28","playedAt":"2024-06-28","playerName":"모토케이","playerRace":"T","playerUserId":"chs9011","opponentName":"유성민","opponentRace":"P","map":"버미어","elo":-11.8,"eloChange":-11.8,"matchType":"3/2(2)","memo":"스폰","result":"lose","isWin":false,"winnerPlayer":"유성민","winnerName":"유성민","winnerRace":"P","losePlayer":"모토케이","loseName":"모토케이","loseRace":"T","winnerSoopUserId":"","winnerUserId":"","loseSoopUserId":"chs9011","loserSoopUserId":"chs9011","loseUserId":"chs9011","loserUserId":"chs9011"},{"id":"chs9011_2024-06-28_유성민_P_폴리포이드_-12.9_3/2(1)_스폰","date":"2024-06-28","standardDate":"2024-06-28","playedAt":"2024-06-28","playerName":"모토케이","playerRace":"T","playerUserId":"chs9011","opponentName":"유성민","opponentRace":"P","map":"폴리포이드","elo":-12.9,"eloChange":-12.9,"matchType":"3/2(1)","memo":"스폰","result":"lose","isWin":false,"winnerPlayer":"유성민","winnerName":"유성민","winnerRace":"P","losePlayer":"모토케이","loseName":"모토케이","loseRace":"T","winnerSoopUserId":"","winnerUserId":"","loseSoopUserId":"chs9011","loserSoopUserId":"chs9011","loseUserId":"chs9011","loserUserId":"chs9011"},{"id":"chs9011_2024-06-22_멍이_P_버미어_-4.6_3/2(2)_3/2_2경기","date":"2024-06-22","standardDate":"2024-06-22","playedAt":"2024-06-22","playerName":"모토케이","playerRace":"T","playerUserId":"chs9011","opponentName":"멍이","opponentRace":"P","map":"버미어","elo":-4.6,"eloChange":-4.6,"matchType":"3/2(2)","memo":"3/2 2경기","result":"lose","isWin":false,"winnerPlayer":"멍이","winnerName":"멍이","winnerRace":"P","losePlayer":"모토케이","loseName":"모토케이","loseRace":"T","winnerSoopUserId":"","winnerUserId":"","loseSoopUserId":"chs9011","loserSoopUserId":"chs9011","loseUserId":"chs9011","loserUserId":"chs9011"},{"id":"chs9011_2024-06-22_멍이_P_폴리포이드_-4.9_3/2(1)_3/2_1경기","date":"2024-06-22","standardDate":"2024-06-22","playedAt":"2024-06-22","playerName":"모토케이","playerRace":"T","playerUserId":"chs9011","opponentName":"멍이","opponentRace":"P","map":"폴리포이드","elo":-4.9,"eloChange":-4.9,"matchType":"3/2(1)","memo":"3/2 1경기","result":"lose","isWin":false,"winnerPlayer":"멍이","winnerName":"멍이","winnerRace":"P","losePlayer":"모토케이","loseName":"모토케이","loseRace":"T","winnerSoopUserId":"","winnerUserId":"","loseSoopUserId":"chs9011","loserSoopUserId":"chs9011","loseUserId":"chs9011","loserUserId":"chs9011"},{"id":"chs9011_2024-06-21_유성민_P_레트로_21.7_3/2(3)_3","date":"2024-06-21","standardDate":"2024-06-21","playedAt":"2024-06-21","playerName":"모토케이","playerRace":"T","playerUserId":"chs9011","opponentName":"유성민","opponentRace":"P","map":"레트로","elo":21.7,"eloChange":21.7,"matchType":"3/2(3)","memo":"3","result":"win","isWin":true,"winnerPlayer":"모토케이","winnerName":"모토케이","winnerRace":"T","losePlayer":"유성민","loseName":"유성민","loseRace":"P","winnerSoopUserId":"chs9011","winnerUserId":"chs9011","loseSoopUserId":"","loserSoopUserId":"","loseUserId":"","loserUserId":""},{"id":"chs9011_2024-06-21_유성민_P_폴리포이드_-11.3_3/2(2)_2","date":"2024-06-21","standardDate":"2024-06-21","playedAt":"2024-06-21","playerName":"모토케이","playerRace":"T","playerUserId":"chs9011","opponentName":"유성민","opponentRace":"P","map":"폴리포이드","elo":-11.3,"eloChange":-11.3,"matchType":"3/2(2)","memo":"2","result":"lose","isWin":false,"winnerPlayer":"유성민","winnerName":"유성민","winnerRace":"P","losePlayer":"모토케이","loseName":"모토케이","loseRace":"T","winnerSoopUserId":"","winnerUserId":"","loseSoopUserId":"chs9011","loserSoopUserId":"chs9011","loseUserId":"chs9011","loserUserId":"chs9011"},{"id":"chs9011_2024-06-21_유성민_P_폴리포이드_22.6_3/2(1)_3/2_[1]","date":"2024-06-21","standardDate":"2024-06-21","playedAt":"2024-06-21","playerName":"모토케이","playerRace":"T","playerUserId":"chs9011","opponentName":"유성민","opponentRace":"P","map":"폴리포이드","elo":22.6,"eloChange":22.6,"matchType":"3/2(1)","memo":"3/2 [1]","result":"win","isWin":true,"winnerPlayer":"모토케이","winnerName":"모토케이","winnerRace":"T","losePlayer":"유성민","loseName":"유성민","loseRace":"P","winnerSoopUserId":"chs9011","winnerUserId":"chs9011","loseSoopUserId":"","loserSoopUserId":"","loseUserId":"","loserUserId":""},{"id":"chs9011_2024-06-18_유성민_P_버미어_-5.7_3/2(2)_스폰","date":"2024-06-18","standardDate":"2024-06-18","playedAt":"2024-06-18","playerName":"모토케이","playerRace":"T","playerUserId":"chs9011","opponentName":"유성민","opponentRace":"P","map":"버미어","elo":-5.7,"eloChange":-5.7,"matchType":"3/2(2)","memo":"스폰","result":"lose","isWin":false,"winnerPlayer":"유성민","winnerName":"유성민","winnerRace":"P","losePlayer":"모토케이","loseName":"모토케이","loseRace":"T","winnerSoopUserId":"","winnerUserId":"","loseSoopUserId":"chs9011","loserSoopUserId":"chs9011","loseUserId":"chs9011","loserUserId":"chs9011"},{"id":"chs9011_2024-06-18_유성민_P_폴리포이드_-6_3/2(1)_리스폰","date":"2024-06-18","standardDate":"2024-06-18","playedAt":"2024-06-18","playerName":"모토케이","playerRace":"T","playerUserId":"chs9011","opponentName":"유성민","opponentRace":"P","map":"폴리포이드","elo":-6,"eloChange":-6,"matchType":"3/2(1)","memo":"리스폰","result":"lose","isWin":false,"winnerPlayer":"유성민","winnerName":"유성민","winnerRace":"P","losePlayer":"모토케이","loseName":"모토케이","loseRace":"T","winnerSoopUserId":"","winnerUserId":"","loseSoopUserId":"chs9011","loserSoopUserId":"chs9011","loseUserId":"chs9011","loserUserId":"chs9011"},{"id":"chs9011_2024-06-18_유성민_P_폴리포이드_-6.4_3/2(3)_스폰","date":"2024-06-18","standardDate":"2024-06-18","playedAt":"2024-06-18","playerName":"모토케이","playerRace":"T","playerUserId":"chs9011","opponentName":"유성민","opponentRace":"P","map":"폴리포이드","elo":-6.4,"eloChange":-6.4,"matchType":"3/2(3)","memo":"스폰","result":"lose","isWin":false,"winnerPlayer":"유성민","winnerName":"유성민","winnerRace":"P","losePlayer":"모토케이","loseName":"모토케이","loseRace":"T","winnerSoopUserId":"","winnerUserId":"","loseSoopUserId":"chs9011","loserSoopUserId":"chs9011","loseUserId":"chs9011","loserUserId":"chs9011"},{"id":"chs9011_2024-06-18_유성민_P_폴리포이드_-6.8_3/2(2)_스폰","date":"2024-06-18","standardDate":"2024-06-18","playedAt":"2024-06-18","playerName":"모토케이","playerRace":"T","playerUserId":"chs9011","opponentName":"유성민","opponentRace":"P","map":"폴리포이드","elo":-6.8,"eloChange":-6.8,"matchType":"3/2(2)","memo":"스폰","result":"lose","isWin":false,"winnerPlayer":"유성민","winnerName":"유성민","winnerRace":"P","losePlayer":"모토케이","loseName":"모토케이","loseRace":"T","winnerSoopUserId":"","winnerUserId":"","loseSoopUserId":"chs9011","loserSoopUserId":"chs9011","loseUserId":"chs9011","loserUserId":"chs9011"},{"id":"chs9011_2024-06-18_유성민_P_버미어_26.7_3/2(1)_스폰","date":"2024-06-18","standardDate":"2024-06-18","playedAt":"2024-06-18","playerName":"모토케이","playerRace":"T","playerUserId":"chs9011","opponentName":"유성민","opponentRace":"P","map":"버미어","elo":26.7,"eloChange":26.7,"matchType":"3/2(1)","memo":"스폰","result":"win","isWin":true,"winnerPlayer":"모토케이","winnerName":"모토케이","winnerRace":"T","losePlayer":"유성민","loseName":"유성민","loseRace":"P","winnerSoopUserId":"chs9011","winnerUserId":"chs9011","loseSoopUserId":"","loserSoopUserId":"","loseUserId":"","loserUserId":""},{"id":"chs9011_2024-04-28_경식_Z_레트로_15.8_단판_단판","date":"2024-04-28","standardDate":"2024-04-28","playedAt":"2024-04-28","playerName":"모토케이","playerRace":"T","playerUserId":"chs9011","opponentName":"경식","opponentRace":"Z","map":"레트로","elo":15.8,"eloChange":15.8,"matchType":"단판","memo":"단판","result":"win","isWin":true,"winnerPlayer":"모토케이","winnerName":"모토케이","winnerRace":"T","losePlayer":"경식","loseName":"경식","loseRace":"Z","winnerSoopUserId":"chs9011","winnerUserId":"chs9011","loseSoopUserId":"","loserSoopUserId":"","loseUserId":"","loserUserId":""},{"id":"chs9011_2024-02-22_유성민_P_버미어_-5.8_3/2(2)_스폰","date":"2024-02-22","standardDate":"2024-02-22","playedAt":"2024-02-22","playerName":"모토케이","playerRace":"T","playerUserId":"chs9011","opponentName":"유성민","opponentRace":"P","map":"버미어","elo":-5.8,"eloChange":-5.8,"matchType":"3/2(2)","memo":"스폰","result":"lose","isWin":false,"winnerPlayer":"유성민","winnerName":"유성민","winnerRace":"P","losePlayer":"모토케이","loseName":"모토케이","loseRace":"T","winnerSoopUserId":"","winnerUserId":"","loseSoopUserId":"chs9011","loserSoopUserId":"chs9011","loseUserId":"chs9011","loserUserId":"chs9011"},{"id":"chs9011_2024-02-22_유성민_P_폴리포이드_-6.1_3/2(1)_스폰","date":"2024-02-22","standardDate":"2024-02-22","playedAt":"2024-02-22","playerName":"모토케이","playerRace":"T","playerUserId":"chs9011","opponentName":"유성민","opponentRace":"P","map":"폴리포이드","elo":-6.1,"eloChange":-6.1,"matchType":"3/2(1)","memo":"스폰","result":"lose","isWin":false,"winnerPlayer":"유성민","winnerName":"유성민","winnerRace":"P","losePlayer":"모토케이","loseName":"모토케이","loseRace":"T","winnerSoopUserId":"","winnerUserId":"","loseSoopUserId":"chs9011","loserSoopUserId":"chs9011","loseUserId":"chs9011","loserUserId":"chs9011"},{"id":"chs9011_2024-02-19_유성민_P_버미어_-8.1_3/2(2)_스폰","date":"2024-02-19","standardDate":"2024-02-19","playedAt":"2024-02-19","playerName":"모토케이","playerRace":"T","playerUserId":"chs9011","opponentName":"유성민","opponentRace":"P","map":"버미어","elo":-8.1,"eloChange":-8.1,"matchType":"3/2(2)","memo":"스폰","result":"lose","isWin":false,"winnerPlayer":"유성민","winnerName":"유성민","winnerRace":"P","losePlayer":"모토케이","loseName":"모토케이","loseRace":"T","winnerSoopUserId":"","winnerUserId":"","loseSoopUserId":"chs9011","loserSoopUserId":"chs9011","loseUserId":"chs9011","loserUserId":"chs9011"},{"id":"chs9011_2024-02-19_유성민_P_폴리포이드_-8.7_3/2(1)_스폰","date":"2024-02-19","standardDate":"2024-02-19","playedAt":"2024-02-19","playerName":"모토케이","playerRace":"T","playerUserId":"chs9011","opponentName":"유성민","opponentRace":"P","map":"폴리포이드","elo":-8.7,"eloChange":-8.7,"matchType":"3/2(1)","memo":"스폰","result":"lose","isWin":false,"winnerPlayer":"유성민","winnerName":"유성민","winnerRace":"P","losePlayer":"모토케이","loseName":"모토케이","loseRace":"T","winnerSoopUserId":"","winnerUserId":"","loseSoopUserId":"chs9011","loserSoopUserId":"chs9011","loseUserId":"chs9011","loserUserId":"chs9011"},{"id":"chs9011_2024-02-10_또봉순_Z_버미어_8.6_단판_단판","date":"2024-02-10","standardDate":"2024-02-10","playedAt":"2024-02-10","playerName":"모토케이","playerRace":"T","playerUserId":"chs9011","opponentName":"또봉순","opponentRace":"Z","map":"버미어","elo":8.6,"eloChange":8.6,"matchType":"단판","memo":"단판","result":"win","isWin":true,"winnerPlayer":"모토케이","winnerName":"모토케이","winnerRace":"T","losePlayer":"또봉순","loseName":"또봉순","loseRace":"Z","winnerSoopUserId":"chs9011","winnerUserId":"chs9011","loseSoopUserId":"","loserSoopUserId":"","loseUserId":"","loserUserId":""},{"id":"chs9011_2024-02-10_또봉순_Z_폴리포이드_-25.1_단판_단판","date":"2024-02-10","standardDate":"2024-02-10","playedAt":"2024-02-10","playerName":"모토케이","playerRace":"T","playerUserId":"chs9011","opponentName":"또봉순","opponentRace":"Z","map":"폴리포이드","elo":-25.1,"eloChange":-25.1,"matchType":"단판","memo":"단판","result":"lose","isWin":false,"winnerPlayer":"또봉순","winnerName":"또봉순","winnerRace":"Z","losePlayer":"모토케이","loseName":"모토케이","loseRace":"T","winnerSoopUserId":"","winnerUserId":"","loseSoopUserId":"chs9011","loserSoopUserId":"chs9011","loseUserId":"chs9011","loserUserId":"chs9011"},{"id":"chs9011_2023-10-27_수입뿌드_P_네오실피드_-8.9_단판_2티어_P/L_2세트_3경기","date":"2023-10-27","standardDate":"2023-10-27","playedAt":"2023-10-27","playerName":"모토케이","playerRace":"T","playerUserId":"chs9011","opponentName":"수입뿌드","opponentRace":"P","map":"네오실피드","elo":-8.9,"eloChange":-8.9,"matchType":"단판","memo":"2티어 P/L 2세트 3경기","result":"lose","isWin":false,"winnerPlayer":"수입뿌드","winnerName":"수입뿌드","winnerRace":"P","losePlayer":"모토케이","loseName":"모토케이","loseRace":"T","winnerSoopUserId":"","winnerUserId":"","loseSoopUserId":"chs9011","loserSoopUserId":"chs9011","loseUserId":"chs9011","loserUserId":"chs9011"},{"id":"chs9011_2023-10-27_벤츠_Z_네오실피드_-18.8_단판_2티어_P/L_1세트_1경기","date":"2023-10-27","standardDate":"2023-10-27","playedAt":"2023-10-27","playerName":"모토케이","playerRace":"T","playerUserId":"chs9011","opponentName":"벤츠","opponentRace":"Z","map":"네오실피드","elo":-18.8,"eloChange":-18.8,"matchType":"단판","memo":"2티어 P/L 1세트 1경기","result":"lose","isWin":false,"winnerPlayer":"벤츠","winnerName":"벤츠","winnerRace":"Z","losePlayer":"모토케이","loseName":"모토케이","loseRace":"T","winnerSoopUserId":"","winnerUserId":"","loseSoopUserId":"chs9011","loserSoopUserId":"chs9011","loseUserId":"chs9011","loserUserId":"chs9011"},{"id":"chs9011_2023-10-20_유성민_P_네오실피드_24.3_3/2(3)_3","date":"2023-10-20","standardDate":"2023-10-20","playedAt":"2023-10-20","playerName":"모토케이","playerRace":"T","playerUserId":"chs9011","opponentName":"유성민","opponentRace":"P","map":"네오실피드","elo":24.3,"eloChange":24.3,"matchType":"3/2(3)","memo":"3","result":"win","isWin":true,"winnerPlayer":"모토케이","winnerName":"모토케이","winnerRace":"T","losePlayer":"유성민","loseName":"유성민","loseRace":"P","winnerSoopUserId":"chs9011","winnerUserId":"chs9011","loseSoopUserId":"","loserSoopUserId":"","loseUserId":"","loserUserId":""},{"id":"chs9011_2023-10-20_유성민_P_버미어_-8.3_3/2(2)_2","date":"2023-10-20","standardDate":"2023-10-20","playedAt":"2023-10-20","playerName":"모토케이","playerRace":"T","playerUserId":"chs9011","opponentName":"유성민","opponentRace":"P","map":"버미어","elo":-8.3,"eloChange":-8.3,"matchType":"3/2(2)","memo":"2","result":"lose","isWin":false,"winnerPlayer":"유성민","winnerName":"유성민","winnerRace":"P","losePlayer":"모토케이","loseName":"모토케이","loseRace":"T","winnerSoopUserId":"","winnerUserId":"","loseSoopUserId":"chs9011","loserSoopUserId":"chs9011","loseUserId":"chs9011","loserUserId":"chs9011"},{"id":"chs9011_2023-10-20_유성민_P_폴리포이드_25.4_3/2(1)_1","date":"2023-10-20","standardDate":"2023-10-20","playedAt":"2023-10-20","playerName":"모토케이","playerRace":"T","playerUserId":"chs9011","opponentName":"유성민","opponentRace":"P","map":"폴리포이드","elo":25.4,"eloChange":25.4,"matchType":"3/2(1)","memo":"1","result":"win","isWin":true,"winnerPlayer":"모토케이","winnerName":"모토케이","winnerRace":"T","losePlayer":"유성민","loseName":"유성민","loseRace":"P","winnerSoopUserId":"chs9011","winnerUserId":"chs9011","loseSoopUserId":"","loserSoopUserId":"","loseUserId":"","loserUserId":""},{"id":"chs9011_2023-07-10_파도튜브_P_폴리포이드_-9.9_단판_KCM_레이디스_종족최강전_2023_시즌3_2주차_6경기","date":"2023-07-10","standardDate":"2023-07-10","playedAt":"2023-07-10","playerName":"모토케이","playerRace":"T","playerUserId":"chs9011","opponentName":"파도튜브","opponentRace":"P","map":"폴리포이드","elo":-9.9,"eloChange":-9.9,"matchType":"단판","memo":"KCM 레이디스 종족최강전 2023 시즌3 2주차 6경기","result":"lose","isWin":false,"winnerPlayer":"파도튜브","winnerName":"파도튜브","winnerRace":"P","losePlayer":"모토케이","loseName":"모토케이","loseRace":"T","winnerSoopUserId":"","winnerUserId":"","loseSoopUserId":"chs9011","loserSoopUserId":"chs9011","loseUserId":"chs9011","loserUserId":"chs9011"},{"id":"chs9011_2023-06-10_파메_P_네오실피드_-17.3_단판_NASA_토스ck_5경기","date":"2023-06-10","standardDate":"2023-06-10","playedAt":"2023-06-10","playerName":"모토케이","playerRace":"T","playerUserId":"chs9011","opponentName":"파메","opponentRace":"P","map":"네오실피드","elo":-17.3,"eloChange":-17.3,"matchType":"단판","memo":"NASA 토스ck 5경기","result":"lose","isWin":false,"winnerPlayer":"파메","winnerName":"파메","winnerRace":"P","losePlayer":"모토케이","loseName":"모토케이","loseRace":"T","winnerSoopUserId":"","winnerUserId":"","loseSoopUserId":"chs9011","loserSoopUserId":"chs9011","loseUserId":"chs9011","loserUserId":"chs9011"},{"id":"chs9011_2023-05-29_보혜_P_폴리포이드_-14.9_단판_KCM레이디스_종족최강전_2023_시즌2_7주차_3경기","date":"2023-05-29","standardDate":"2023-05-29","playedAt":"2023-05-29","playerName":"모토케이","playerRace":"T","playerUserId":"chs9011","opponentName":"보혜","opponentRace":"P","map":"폴리포이드","elo":-14.9,"eloChange":-14.9,"matchType":"단판","memo":"KCM레이디스 종족최강전 2023 시즌2 7주차 3경기","result":"lose","isWin":false,"winnerPlayer":"보혜","winnerName":"보혜","winnerRace":"P","losePlayer":"모토케이","loseName":"모토케이","loseRace":"T","winnerSoopUserId":"","winnerUserId":"","loseSoopUserId":"chs9011","loserSoopUserId":"chs9011","loseUserId":"chs9011","loserUserId":"chs9011"},{"id":"chs9011_2023-05-27_남덕선_Z_폴리포이드_15.1_단판_단판","date":"2023-05-27","standardDate":"2023-05-27","playedAt":"2023-05-27","playerName":"모토케이","playerRace":"T","playerUserId":"chs9011","opponentName":"남덕선","opponentRace":"Z","map":"폴리포이드","elo":15.1,"eloChange":15.1,"matchType":"단판","memo":"단판","result":"win","isWin":true,"winnerPlayer":"모토케이","winnerName":"모토케이","winnerRace":"T","losePlayer":"남덕선","loseName":"남덕선","loseRace":"Z","winnerSoopUserId":"chs9011","winnerUserId":"chs9011","loseSoopUserId":"","loserSoopUserId":"","loseUserId":"","loserUserId":""},{"id":"chs9011_2023-05-27_벤츠_Z_폴리포이드_17.5_단판_단판","date":"2023-05-27","standardDate":"2023-05-27","playedAt":"2023-05-27","playerName":"모토케이","playerRace":"T","playerUserId":"chs9011","opponentName":"벤츠","opponentRace":"Z","map":"폴리포이드","elo":17.5,"eloChange":17.5,"matchType":"단판","memo":"단판","result":"win","isWin":true,"winnerPlayer":"모토케이","winnerName":"모토케이","winnerRace":"T","losePlayer":"벤츠","loseName":"벤츠","loseRace":"Z","winnerSoopUserId":"chs9011","winnerUserId":"chs9011","loseSoopUserId":"","loserSoopUserId":"","loseUserId":"","loserUserId":""},{"id":"chs9011_2023-05-08_아재동_Z_폴리포이드_16.1_단판_단판스폰","date":"2023-05-08","standardDate":"2023-05-08","playedAt":"2023-05-08","playerName":"모토케이","playerRace":"T","playerUserId":"chs9011","opponentName":"아재동","opponentRace":"Z","map":"폴리포이드","elo":16.1,"eloChange":16.1,"matchType":"단판","memo":"단판스폰","result":"win","isWin":true,"winnerPlayer":"모토케이","winnerName":"모토케이","winnerRace":"T","losePlayer":"아재동","loseName":"아재동","loseRace":"Z","winnerSoopUserId":"chs9011","winnerUserId":"chs9011","loseSoopUserId":"","loserSoopUserId":"","loseUserId":"","loserUserId":""},{"id":"chs9011_2023-05-01_서도일_Z_네오실피드_-15.3_단판_KCM레이디스_종족최강전_2023_시즌2_3주차_4경기","date":"2023-05-01","standardDate":"2023-05-01","playedAt":"2023-05-01","playerName":"모토케이","playerRace":"T","playerUserId":"chs9011","opponentName":"서도일","opponentRace":"Z","map":"네오실피드","elo":-15.3,"eloChange":-15.3,"matchType":"단판","memo":"KCM레이디스 종족최강전 2023 시즌2 3주차 4경기","result":"lose","isWin":false,"winnerPlayer":"서도일","winnerName":"서도일","winnerRace":"Z","losePlayer":"모토케이","loseName":"모토케이","loseRace":"T","winnerSoopUserId":"","winnerUserId":"","loseSoopUserId":"chs9011","loserSoopUserId":"chs9011","loseUserId":"chs9011","loserUserId":"chs9011"},{"id":"chs9011_2023-05-01_파도튜브_P_폴리포이드_22.7_단판_KCM레이디스_종족최강전_2023_시즌2_3주차_3경기","date":"2023-05-01","standardDate":"2023-05-01","playedAt":"2023-05-01","playerName":"모토케이","playerRace":"T","playerUserId":"chs9011","opponentName":"파도튜브","opponentRace":"P","map":"폴리포이드","elo":22.7,"eloChange":22.7,"matchType":"단판","memo":"KCM레이디스 종족최강전 2023 시즌2 3주차 3경기","result":"win","isWin":true,"winnerPlayer":"모토케이","winnerName":"모토케이","winnerRace":"T","losePlayer":"파도튜브","loseName":"파도튜브","loseRace":"P","winnerSoopUserId":"chs9011","winnerUserId":"chs9011","loseSoopUserId":"","loserSoopUserId":"","loseUserId":"","loserUserId":""},{"id":"chs9011_2023-04-17_유성민_P_네오실피드_-13.6_3/2(3)_스폰","date":"2023-04-17","standardDate":"2023-04-17","playedAt":"2023-04-17","playerName":"모토케이","playerRace":"T","playerUserId":"chs9011","opponentName":"유성민","opponentRace":"P","map":"네오실피드","elo":-13.6,"eloChange":-13.6,"matchType":"3/2(3)","memo":"스폰","result":"lose","isWin":false,"winnerPlayer":"유성민","winnerName":"유성민","winnerRace":"P","losePlayer":"모토케이","loseName":"모토케이","loseRace":"T","winnerSoopUserId":"","winnerUserId":"","loseSoopUserId":"chs9011","loserSoopUserId":"chs9011","loseUserId":"chs9011","loserUserId":"chs9011"},{"id":"chs9011_2023-04-17_유성민_P_버미어_20.2_3/2(2)_스폰","date":"2023-04-17","standardDate":"2023-04-17","playedAt":"2023-04-17","playerName":"모토케이","playerRace":"T","playerUserId":"chs9011","opponentName":"유성민","opponentRace":"P","map":"버미어","elo":20.2,"eloChange":20.2,"matchType":"3/2(2)","memo":"스폰","result":"win","isWin":true,"winnerPlayer":"모토케이","winnerName":"모토케이","winnerRace":"T","losePlayer":"유성민","loseName":"유성민","loseRace":"P","winnerSoopUserId":"chs9011","winnerUserId":"chs9011","loseSoopUserId":"","loserSoopUserId":"","loseUserId":"","loserUserId":""},{"id":"chs9011_2023-04-17_유성민_P_폴리포이드_-13_3/2(1)_스폰","date":"2023-04-17","standardDate":"2023-04-17","playedAt":"2023-04-17","playerName":"모토케이","playerRace":"T","playerUserId":"chs9011","opponentName":"유성민","opponentRace":"P","map":"폴리포이드","elo":-13,"eloChange":-13,"matchType":"3/2(1)","memo":"스폰","result":"lose","isWin":false,"winnerPlayer":"유성민","winnerName":"유성민","winnerRace":"P","losePlayer":"모토케이","loseName":"모토케이","loseRace":"T","winnerSoopUserId":"","winnerUserId":"","loseSoopUserId":"chs9011","loserSoopUserId":"chs9011","loseUserId":"chs9011","loserUserId":"chs9011"},{"id":"chs9011_2022-10-02_트슈_P_네오실피드_-12.4_7/4(3)_좋스파리그_B조_3경기_JSAvs고대_3세트","date":"2022-10-02","standardDate":"2022-10-02","playedAt":"2022-10-02","playerName":"모토케이","playerRace":"T","playerUserId":"chs9011","opponentName":"트슈","opponentRace":"P","map":"네오실피드","elo":-12.4,"eloChange":-12.4,"matchType":"7/4(3)","memo":"좋스파리그 B조 3경기 JSAvs고대 3세트","result":"lose","isWin":false,"winnerPlayer":"트슈","winnerName":"트슈","winnerRace":"P","losePlayer":"모토케이","loseName":"모토케이","loseRace":"T","winnerSoopUserId":"","winnerUserId":"","loseSoopUserId":"chs9011","loserSoopUserId":"chs9011","loseUserId":"chs9011","loserUserId":"chs9011"},{"id":"chs9011_2022-10-02_파메_P_투혼_-18.2_7/4(3)_좋스파리그_B조_2경기_MSGvs고대_3세트","date":"2022-10-02","standardDate":"2022-10-02","playedAt":"2022-10-02","playerName":"모토케이","playerRace":"T","playerUserId":"chs9011","opponentName":"파메","opponentRace":"P","map":"투혼","elo":-18.2,"eloChange":-18.2,"matchType":"7/4(3)","memo":"좋스파리그 B조 2경기 MSGvs고대 3세트","result":"lose","isWin":false,"winnerPlayer":"파메","winnerName":"파메","winnerRace":"P","losePlayer":"모토케이","loseName":"모토케이","loseRace":"T","winnerSoopUserId":"","winnerUserId":"","loseSoopUserId":"chs9011","loserSoopUserId":"chs9011","loseUserId":"chs9011","loserUserId":"chs9011"},{"id":"chs9011_2022-09-25_서도일_Z_네오실피드_21.5_7/4(4)_대학대전_CP_vs_GOU_(4)","date":"2022-09-25","standardDate":"2022-09-25","playedAt":"2022-09-25","playerName":"모토케이","playerRace":"T","playerUserId":"chs9011","opponentName":"서도일","opponentRace":"Z","map":"네오실피드","elo":21.5,"eloChange":21.5,"matchType":"7/4(4)","memo":"대학대전 CP vs GOU (4)","result":"win","isWin":true,"winnerPlayer":"모토케이","winnerName":"모토케이","winnerRace":"T","losePlayer":"서도일","loseName":"서도일","loseRace":"Z","winnerSoopUserId":"chs9011","winnerUserId":"chs9011","loseSoopUserId":"","loserSoopUserId":"","loseUserId":"","loserUserId":""},{"id":"chs9011_2022-09-21_파메_P_폴리포이드_17.7_단판_대학대전_MSG_vs_GOU_(에이스결정전)","date":"2022-09-21","standardDate":"2022-09-21","playedAt":"2022-09-21","playerName":"모토케이","playerRace":"T","playerUserId":"chs9011","opponentName":"파메","opponentRace":"P","map":"폴리포이드","elo":17.7,"eloChange":17.7,"matchType":"단판","memo":"대학대전 MSG vs GOU (에이스결정전)","result":"win","isWin":true,"winnerPlayer":"모토케이","winnerName":"모토케이","winnerRace":"T","losePlayer":"파메","loseName":"파메","loseRace":"P","winnerSoopUserId":"chs9011","winnerUserId":"chs9011","loseSoopUserId":"","loserSoopUserId":"","loseUserId":"","loserUserId":""},{"id":"chs9011_2022-08-29_트슈_P_블루스톰_24.6_3/2(3)_.","date":"2022-08-29","standardDate":"2022-08-29","playedAt":"2022-08-29","playerName":"모토케이","playerRace":"T","playerUserId":"chs9011","opponentName":"트슈","opponentRace":"P","map":"블루스톰","elo":24.6,"eloChange":24.6,"matchType":"3/2(3)","memo":".","result":"win","isWin":true,"winnerPlayer":"모토케이","winnerName":"모토케이","winnerRace":"T","losePlayer":"트슈","loseName":"트슈","loseRace":"P","winnerSoopUserId":"chs9011","winnerUserId":"chs9011","loseSoopUserId":"","loserSoopUserId":"","loseUserId":"","loserUserId":""},{"id":"chs9011_2022-08-29_트슈_P_네오실피드_-8_3/2(2)_.","date":"2022-08-29","standardDate":"2022-08-29","playedAt":"2022-08-29","playerName":"모토케이","playerRace":"T","playerUserId":"chs9011","opponentName":"트슈","opponentRace":"P","map":"네오실피드","elo":-8,"eloChange":-8,"matchType":"3/2(2)","memo":".","result":"lose","isWin":false,"winnerPlayer":"트슈","winnerName":"트슈","winnerRace":"P","losePlayer":"모토케이","loseName":"모토케이","loseRace":"T","winnerSoopUserId":"","winnerUserId":"","loseSoopUserId":"chs9011","loserSoopUserId":"chs9011","loseUserId":"chs9011","loserUserId":"chs9011"},{"id":"chs9011_2022-08-29_트슈_P_폴리포이드_25.6_3/2(1)_.","date":"2022-08-29","standardDate":"2022-08-29","playedAt":"2022-08-29","playerName":"모토케이","playerRace":"T","playerUserId":"chs9011","opponentName":"트슈","opponentRace":"P","map":"폴리포이드","elo":25.6,"eloChange":25.6,"matchType":"3/2(1)","memo":".","result":"win","isWin":true,"winnerPlayer":"모토케이","winnerName":"모토케이","winnerRace":"T","losePlayer":"트슈","loseName":"트슈","loseRace":"P","winnerSoopUserId":"chs9011","winnerUserId":"chs9011","loseSoopUserId":"","loserSoopUserId":"","loseUserId":"","loserUserId":""},{"id":"chs9011_2022-08-10_마이티베어_P_블루_스톰_18.8_3/2(3)_3","date":"2022-08-10","standardDate":"2022-08-10","playedAt":"2022-08-10","playerName":"모토케이","playerRace":"T","playerUserId":"chs9011","opponentName":"마이티베어","opponentRace":"P","map":"블루 스톰","elo":18.8,"eloChange":18.8,"matchType":"3/2(3)","memo":"3","result":"win","isWin":true,"winnerPlayer":"모토케이","winnerName":"모토케이","winnerRace":"T","losePlayer":"마이티베어","loseName":"마이티베어","loseRace":"P","winnerSoopUserId":"chs9011","winnerUserId":"chs9011","loseSoopUserId":"","loserSoopUserId":"","loseUserId":"","loserUserId":""},{"id":"chs9011_2022-08-10_마이티베어_P_네오실피드_20.6_3/2(2)_2","date":"2022-08-10","standardDate":"2022-08-10","playedAt":"2022-08-10","playerName":"모토케이","playerRace":"T","playerUserId":"chs9011","opponentName":"마이티베어","opponentRace":"P","map":"네오실피드","elo":20.6,"eloChange":20.6,"matchType":"3/2(2)","memo":"2","result":"win","isWin":true,"winnerPlayer":"모토케이","winnerName":"모토케이","winnerRace":"T","losePlayer":"마이티베어","loseName":"마이티베어","loseRace":"P","winnerSoopUserId":"chs9011","winnerUserId":"chs9011","loseSoopUserId":"","loserSoopUserId":"","loseUserId":"","loserUserId":""},{"id":"chs9011_2022-08-10_마이티베어_P_블루_스톰_-12.5_3/2(1)_1","date":"2022-08-10","standardDate":"2022-08-10","playedAt":"2022-08-10","playerName":"모토케이","playerRace":"T","playerUserId":"chs9011","opponentName":"마이티베어","opponentRace":"P","map":"블루 스톰","elo":-12.5,"eloChange":-12.5,"matchType":"3/2(1)","memo":"1","result":"lose","isWin":false,"winnerPlayer":"마이티베어","winnerName":"마이티베어","winnerRace":"P","losePlayer":"모토케이","loseName":"모토케이","loseRace":"T","winnerSoopUserId":"","winnerUserId":"","loseSoopUserId":"chs9011","loserSoopUserId":"chs9011","loseUserId":"chs9011","loserUserId":"chs9011"},{"id":"chs9011_2022-08-06_마이티베어_P_블루_스톰_-14.5_3/2(3)_3","date":"2022-08-06","standardDate":"2022-08-06","playedAt":"2022-08-06","playerName":"모토케이","playerRace":"T","playerUserId":"chs9011","opponentName":"마이티베어","opponentRace":"P","map":"블루 스톰","elo":-14.5,"eloChange":-14.5,"matchType":"3/2(3)","memo":"3","result":"lose","isWin":false,"winnerPlayer":"마이티베어","winnerName":"마이티베어","winnerRace":"P","losePlayer":"모토케이","loseName":"모토케이","loseRace":"T","winnerSoopUserId":"","winnerUserId":"","loseSoopUserId":"chs9011","loserSoopUserId":"chs9011","loseUserId":"chs9011","loserUserId":"chs9011"},{"id":"chs9011_2022-08-06_마이티베어_P_네오실피드_19.2_3/2(2)_2","date":"2022-08-06","standardDate":"2022-08-06","playedAt":"2022-08-06","playerName":"모토케이","playerRace":"T","playerUserId":"chs9011","opponentName":"마이티베어","opponentRace":"P","map":"네오실피드","elo":19.2,"eloChange":19.2,"matchType":"3/2(2)","memo":"2","result":"win","isWin":true,"winnerPlayer":"모토케이","winnerName":"모토케이","winnerRace":"T","losePlayer":"마이티베어","loseName":"마이티베어","loseRace":"P","winnerSoopUserId":"chs9011","winnerUserId":"chs9011","loseSoopUserId":"","loserSoopUserId":"","loseUserId":"","loserUserId":""},{"id":"chs9011_2022-08-06_마이티베어_P_블루_스톰_-14.1_3/2(1)_1","date":"2022-08-06","standardDate":"2022-08-06","playedAt":"2022-08-06","playerName":"모토케이","playerRace":"T","playerUserId":"chs9011","opponentName":"마이티베어","opponentRace":"P","map":"블루 스톰","elo":-14.1,"eloChange":-14.1,"matchType":"3/2(1)","memo":"1","result":"lose","isWin":false,"winnerPlayer":"마이티베어","winnerName":"마이티베어","winnerRace":"P","losePlayer":"모토케이","loseName":"모토케이","loseRace":"T","winnerSoopUserId":"","winnerUserId":"","loseSoopUserId":"chs9011","loserSoopUserId":"chs9011","loseUserId":"chs9011","loserUserId":"chs9011"},{"id":"chs9011_2022-08-02_마이티베어_P_네오실피드_-18.1_3/2(3)_.","date":"2022-08-02","standardDate":"2022-08-02","playedAt":"2022-08-02","playerName":"모토케이","playerRace":"T","playerUserId":"chs9011","opponentName":"마이티베어","opponentRace":"P","map":"네오실피드","elo":-18.1,"eloChange":-18.1,"matchType":"3/2(3)","memo":".","result":"lose","isWin":false,"winnerPlayer":"마이티베어","winnerName":"마이티베어","winnerRace":"P","losePlayer":"모토케이","loseName":"모토케이","loseRace":"T","winnerSoopUserId":"","winnerUserId":"","loseSoopUserId":"chs9011","loserSoopUserId":"chs9011","loseUserId":"chs9011","loserUserId":"chs9011"},{"id":"chs9011_2022-08-02_마이티베어_P_블루_스톰_-19.9_3/2(2)_.","date":"2022-08-02","standardDate":"2022-08-02","playedAt":"2022-08-02","playerName":"모토케이","playerRace":"T","playerUserId":"chs9011","opponentName":"마이티베어","opponentRace":"P","map":"블루 스톰","elo":-19.9,"eloChange":-19.9,"matchType":"3/2(2)","memo":".","result":"lose","isWin":false,"winnerPlayer":"마이티베어","winnerName":"마이티베어","winnerRace":"P","losePlayer":"모토케이","loseName":"모토케이","loseRace":"T","winnerSoopUserId":"","winnerUserId":"","loseSoopUserId":"chs9011","loserSoopUserId":"chs9011","loseUserId":"chs9011","loserUserId":"chs9011"},{"id":"chs9011_2022-08-02_마이티베어_P_네오실피드_13.3_3/2(1)_.","date":"2022-08-02","standardDate":"2022-08-02","playedAt":"2022-08-02","playerName":"모토케이","playerRace":"T","playerUserId":"chs9011","opponentName":"마이티베어","opponentRace":"P","map":"네오실피드","elo":13.3,"eloChange":13.3,"matchType":"3/2(1)","memo":".","result":"win","isWin":true,"winnerPlayer":"모토케이","winnerName":"모토케이","winnerRace":"T","losePlayer":"마이티베어","loseName":"마이티베어","loseRace":"P","winnerSoopUserId":"chs9011","winnerUserId":"chs9011","loseSoopUserId":"","loserSoopUserId":"","loseUserId":"","loserUserId":""},{"id":"chs9011_2022-08-02_탱크_P_네오실피드_-5.7_3/2(2)_2","date":"2022-08-02","standardDate":"2022-08-02","playedAt":"2022-08-02","playerName":"모토케이","playerRace":"T","playerUserId":"chs9011","opponentName":"탱크","opponentRace":"P","map":"네오실피드","elo":-5.7,"eloChange":-5.7,"matchType":"3/2(2)","memo":"2","result":"lose","isWin":false,"winnerPlayer":"탱크","winnerName":"탱크","winnerRace":"P","losePlayer":"모토케이","loseName":"모토케이","loseRace":"T","winnerSoopUserId":"","winnerUserId":"","loseSoopUserId":"chs9011","loserSoopUserId":"chs9011","loseUserId":"chs9011","loserUserId":"chs9011"},{"id":"chs9011_2022-08-02_탱크_P_폴리포이드_-6_3/2(1)_1","date":"2022-08-02","standardDate":"2022-08-02","playedAt":"2022-08-02","playerName":"모토케이","playerRace":"T","playerUserId":"chs9011","opponentName":"탱크","opponentRace":"P","map":"폴리포이드","elo":-6,"eloChange":-6,"matchType":"3/2(1)","memo":"1","result":"lose","isWin":false,"winnerPlayer":"탱크","winnerName":"탱크","winnerRace":"P","losePlayer":"모토케이","loseName":"모토케이","loseRace":"T","winnerSoopUserId":"","winnerUserId":"","loseSoopUserId":"chs9011","loserSoopUserId":"chs9011","loseUserId":"chs9011","loserUserId":"chs9011"},{"id":"chs9011_2022-08-02_보혜_P_블루_스톰_-11.8_3/2(3)_.","date":"2022-08-02","standardDate":"2022-08-02","playedAt":"2022-08-02","playerName":"모토케이","playerRace":"T","playerUserId":"chs9011","opponentName":"보혜","opponentRace":"P","map":"블루 스톰","elo":-11.8,"eloChange":-11.8,"matchType":"3/2(3)","memo":".","result":"lose","isWin":false,"winnerPlayer":"보혜","winnerName":"보혜","winnerRace":"P","losePlayer":"모토케이","loseName":"모토케이","loseRace":"T","winnerSoopUserId":"","winnerUserId":"","loseSoopUserId":"chs9011","loserSoopUserId":"chs9011","loseUserId":"chs9011","loserUserId":"chs9011"},{"id":"chs9011_2022-08-02_보혜_P_블루_스톰_22_3/2(2)_.","date":"2022-08-02","standardDate":"2022-08-02","playedAt":"2022-08-02","playerName":"모토케이","playerRace":"T","playerUserId":"chs9011","opponentName":"보혜","opponentRace":"P","map":"블루 스톰","elo":22,"eloChange":22,"matchType":"3/2(2)","memo":".","result":"win","isWin":true,"winnerPlayer":"모토케이","winnerName":"모토케이","winnerRace":"T","losePlayer":"보혜","loseName":"보혜","loseRace":"P","winnerSoopUserId":"chs9011","winnerUserId":"chs9011","loseSoopUserId":"","loserSoopUserId":"","loseUserId":"","loserUserId":""},{"id":"chs9011_2022-08-02_보혜_P_네오실피드_-10.8_3/2(1)_.","date":"2022-08-02","standardDate":"2022-08-02","playedAt":"2022-08-02","playerName":"모토케이","playerRace":"T","playerUserId":"chs9011","opponentName":"보혜","opponentRace":"P","map":"네오실피드","elo":-10.8,"eloChange":-10.8,"matchType":"3/2(1)","memo":".","result":"lose","isWin":false,"winnerPlayer":"보혜","winnerName":"보혜","winnerRace":"P","losePlayer":"모토케이","loseName":"모토케이","loseRace":"T","winnerSoopUserId":"","winnerUserId":"","loseSoopUserId":"chs9011","loserSoopUserId":"chs9011","loseUserId":"chs9011","loserUserId":"chs9011"},{"id":"chs9011_2022-08-01_수입뿌드_P_네오실피드_-9.9_3/2(2)_.","date":"2022-08-01","standardDate":"2022-08-01","playedAt":"2022-08-01","playerName":"모토케이","playerRace":"T","playerUserId":"chs9011","opponentName":"수입뿌드","opponentRace":"P","map":"네오실피드","elo":-9.9,"eloChange":-9.9,"matchType":"3/2(2)","memo":".","result":"lose","isWin":false,"winnerPlayer":"수입뿌드","winnerName":"수입뿌드","winnerRace":"P","losePlayer":"모토케이","loseName":"모토케이","loseRace":"T","winnerSoopUserId":"","winnerUserId":"","loseSoopUserId":"chs9011","loserSoopUserId":"chs9011","loseUserId":"chs9011","loserUserId":"chs9011"},{"id":"chs9011_2022-08-01_수입뿌드_P_폴리포이드_-10.8_3/2(1)_.","date":"2022-08-01","standardDate":"2022-08-01","playedAt":"2022-08-01","playerName":"모토케이","playerRace":"T","playerUserId":"chs9011","opponentName":"수입뿌드","opponentRace":"P","map":"폴리포이드","elo":-10.8,"eloChange":-10.8,"matchType":"3/2(1)","memo":".","result":"lose","isWin":false,"winnerPlayer":"수입뿌드","winnerName":"수입뿌드","winnerRace":"P","losePlayer":"모토케이","loseName":"모토케이","loseRace":"T","winnerSoopUserId":"","winnerUserId":"","loseSoopUserId":"chs9011","loserSoopUserId":"chs9011","loseUserId":"chs9011","loserUserId":"chs9011"},{"id":"chs9011_2022-08-01_탱크_P_네오실피드_-7.2_3/2(2)_2","date":"2022-08-01","standardDate":"2022-08-01","playedAt":"2022-08-01","playerName":"모토케이","playerRace":"T","playerUserId":"chs9011","opponentName":"탱크","opponentRace":"P","map":"네오실피드","elo":-7.2,"eloChange":-7.2,"matchType":"3/2(2)","memo":"2","result":"lose","isWin":false,"winnerPlayer":"탱크","winnerName":"탱크","winnerRace":"P","losePlayer":"모토케이","loseName":"모토케이","loseRace":"T","winnerSoopUserId":"","winnerUserId":"","loseSoopUserId":"chs9011","loserSoopUserId":"chs9011","loseUserId":"chs9011","loserUserId":"chs9011"},{"id":"chs9011_2022-08-01_탱크_P_폴리포이드_-7.7_3/2(1)_1","date":"2022-08-01","standardDate":"2022-08-01","playedAt":"2022-08-01","playerName":"모토케이","playerRace":"T","playerUserId":"chs9011","opponentName":"탱크","opponentRace":"P","map":"폴리포이드","elo":-7.7,"eloChange":-7.7,"matchType":"3/2(1)","memo":"1","result":"lose","isWin":false,"winnerPlayer":"탱크","winnerName":"탱크","winnerRace":"P","losePlayer":"모토케이","loseName":"모토케이","loseRace":"T","winnerSoopUserId":"","winnerUserId":"","loseSoopUserId":"chs9011","loserSoopUserId":"chs9011","loseUserId":"chs9011","loserUserId":"chs9011"},{"id":"chs9011_2022-08-01_수입뿌드_P_투혼_-10.2_단판_1,2티어_테란vs토스ck_2세트_3경기","date":"2022-08-01","standardDate":"2022-08-01","playedAt":"2022-08-01","playerName":"모토케이","playerRace":"T","playerUserId":"chs9011","opponentName":"수입뿌드","opponentRace":"P","map":"투혼","elo":-10.2,"eloChange":-10.2,"matchType":"단판","memo":"1,2티어 테란vs토스ck 2세트 3경기","result":"lose","isWin":false,"winnerPlayer":"수입뿌드","winnerName":"수입뿌드","winnerRace":"P","losePlayer":"모토케이","loseName":"모토케이","loseRace":"T","winnerSoopUserId":"","winnerUserId":"","loseSoopUserId":"chs9011","loserSoopUserId":"chs9011","loseUserId":"chs9011","loserUserId":"chs9011"},{"id":"chs9011_2022-08-01_탱크_P_폴리포이드_-8.9_단판_1,2티어_테란vs토스ck_1세트_2경기","date":"2022-08-01","standardDate":"2022-08-01","playedAt":"2022-08-01","playerName":"모토케이","playerRace":"T","playerUserId":"chs9011","opponentName":"탱크","opponentRace":"P","map":"폴리포이드","elo":-8.9,"eloChange":-8.9,"matchType":"단판","memo":"1,2티어 테란vs토스ck 1세트 2경기","result":"lose","isWin":false,"winnerPlayer":"탱크","winnerName":"탱크","winnerRace":"P","losePlayer":"모토케이","loseName":"모토케이","loseRace":"T","winnerSoopUserId":"","winnerUserId":"","loseSoopUserId":"chs9011","loserSoopUserId":"chs9011","loseUserId":"chs9011","loserUserId":"chs9011"},{"id":"chs9011_2022-08-01_안아_P_블루스톰_15.6_3/2(2)_3/2","date":"2022-08-01","standardDate":"2022-08-01","playedAt":"2022-08-01","playerName":"모토케이","playerRace":"T","playerUserId":"chs9011","opponentName":"안아","opponentRace":"P","map":"블루스톰","elo":15.6,"eloChange":15.6,"matchType":"3/2(2)","memo":"3/2","result":"win","isWin":true,"winnerPlayer":"모토케이","winnerName":"모토케이","winnerRace":"T","losePlayer":"안아","loseName":"안아","loseRace":"P","winnerSoopUserId":"chs9011","winnerUserId":"chs9011","loseSoopUserId":"","loserSoopUserId":"","loseUserId":"","loserUserId":""},{"id":"chs9011_2022-08-01_안아_P_폴리포이드_17.1_3/2(1)_3/2","date":"2022-08-01","standardDate":"2022-08-01","playedAt":"2022-08-01","playerName":"모토케이","playerRace":"T","playerUserId":"chs9011","opponentName":"안아","opponentRace":"P","map":"폴리포이드","elo":17.1,"eloChange":17.1,"matchType":"3/2(1)","memo":"3/2","result":"win","isWin":true,"winnerPlayer":"모토케이","winnerName":"모토케이","winnerRace":"T","losePlayer":"안아","loseName":"안아","loseRace":"P","winnerSoopUserId":"chs9011","winnerUserId":"chs9011","loseSoopUserId":"","loserSoopUserId":"","loseUserId":"","loserUserId":""},{"id":"chs9011_2022-07-31_픽서_P_블루_스톰_-12.5_3/2(2)_픽서_승","date":"2022-07-31","standardDate":"2022-07-31","playedAt":"2022-07-31","playerName":"모토케이","playerRace":"T","playerUserId":"chs9011","opponentName":"픽서","opponentRace":"P","map":"블루 스톰","elo":-12.5,"eloChange":-12.5,"matchType":"3/2(2)","memo":"픽서 승","result":"lose","isWin":false,"winnerPlayer":"픽서","winnerName":"픽서","winnerRace":"P","losePlayer":"모토케이","loseName":"모토케이","loseRace":"T","winnerSoopUserId":"","winnerUserId":"","loseSoopUserId":"chs9011","loserSoopUserId":"chs9011","loseUserId":"chs9011","loserUserId":"chs9011"},{"id":"chs9011_2022-07-31_픽서_P_네오실피드_-13.8_3/2(1)_픽서_승","date":"2022-07-31","standardDate":"2022-07-31","playedAt":"2022-07-31","playerName":"모토케이","playerRace":"T","playerUserId":"chs9011","opponentName":"픽서","opponentRace":"P","map":"네오실피드","elo":-13.8,"eloChange":-13.8,"matchType":"3/2(1)","memo":"픽서 승","result":"lose","isWin":false,"winnerPlayer":"픽서","winnerName":"픽서","winnerRace":"P","losePlayer":"모토케이","loseName":"모토케이","loseRace":"T","winnerSoopUserId":"","winnerUserId":"","loseSoopUserId":"chs9011","loserSoopUserId":"chs9011","loseUserId":"chs9011","loserUserId":"chs9011"},{"id":"chs9011_2022-07-31_토스봇_P_블루_스톰_-12.6_3/2(3)_3","date":"2022-07-31","standardDate":"2022-07-31","playedAt":"2022-07-31","playerName":"모토케이","playerRace":"T","playerUserId":"chs9011","opponentName":"토스봇","opponentRace":"P","map":"블루 스톰","elo":-12.6,"eloChange":-12.6,"matchType":"3/2(3)","memo":"3","result":"lose","isWin":false,"winnerPlayer":"토스봇","winnerName":"토스봇","winnerRace":"P","losePlayer":"모토케이","loseName":"모토케이","loseRace":"T","winnerSoopUserId":"","winnerUserId":"","loseSoopUserId":"chs9011","loserSoopUserId":"chs9011","loseUserId":"chs9011","loserUserId":"chs9011"},{"id":"chs9011_2022-07-31_토스봇_P_네오실피드_-13.8_3/2(2)_2","date":"2022-07-31","standardDate":"2022-07-31","playedAt":"2022-07-31","playerName":"모토케이","playerRace":"T","playerUserId":"chs9011","opponentName":"토스봇","opponentRace":"P","map":"네오실피드","elo":-13.8,"eloChange":-13.8,"matchType":"3/2(2)","memo":"2","result":"lose","isWin":false,"winnerPlayer":"토스봇","winnerName":"토스봇","winnerRace":"P","losePlayer":"모토케이","loseName":"모토케이","loseRace":"T","winnerSoopUserId":"","winnerUserId":"","loseSoopUserId":"chs9011","loserSoopUserId":"chs9011","loseUserId":"chs9011","loserUserId":"chs9011"},{"id":"chs9011_2022-07-31_토스봇_P_폴리포이드_20_3/2(1)_1","date":"2022-07-31","standardDate":"2022-07-31","playedAt":"2022-07-31","playerName":"모토케이","playerRace":"T","playerUserId":"chs9011","opponentName":"토스봇","opponentRace":"P","map":"폴리포이드","elo":20,"eloChange":20,"matchType":"3/2(1)","memo":"1","result":"win","isWin":true,"winnerPlayer":"모토케이","winnerName":"모토케이","winnerRace":"T","losePlayer":"토스봇","loseName":"토스봇","loseRace":"P","winnerSoopUserId":"chs9011","winnerUserId":"chs9011","loseSoopUserId":"","loserSoopUserId":"","loseUserId":"","loserUserId":""},{"id":"chs9011_2022-07-31_오뀨_Z_블루_스톰_-10.5_단판_단판","date":"2022-07-31","standardDate":"2022-07-31","playedAt":"2022-07-31","playerName":"모토케이","playerRace":"T","playerUserId":"chs9011","opponentName":"오뀨","opponentRace":"Z","map":"블루 스톰","elo":-10.5,"eloChange":-10.5,"matchType":"단판","memo":"단판","result":"lose","isWin":false,"winnerPlayer":"오뀨","winnerName":"오뀨","winnerRace":"Z","losePlayer":"모토케이","loseName":"모토케이","loseRace":"T","winnerSoopUserId":"","winnerUserId":"","loseSoopUserId":"chs9011","loserSoopUserId":"chs9011","loseUserId":"chs9011","loserUserId":"chs9011"},{"id":"chs9011_2022-07-31_토스봇_P_네오실피드_-13.7_3/2(3)_3","date":"2022-07-31","standardDate":"2022-07-31","playedAt":"2022-07-31","playerName":"모토케이","playerRace":"T","playerUserId":"chs9011","opponentName":"토스봇","opponentRace":"P","map":"네오실피드","elo":-13.7,"eloChange":-13.7,"matchType":"3/2(3)","memo":"3","result":"lose","isWin":false,"winnerPlayer":"토스봇","winnerName":"토스봇","winnerRace":"P","losePlayer":"모토케이","loseName":"모토케이","loseRace":"T","winnerSoopUserId":"","winnerUserId":"","loseSoopUserId":"chs9011","loserSoopUserId":"chs9011","loseUserId":"chs9011","loserUserId":"chs9011"},{"id":"chs9011_2022-07-31_토스봇_P_블루_스톰_-15.1_3/2(2)_2","date":"2022-07-31","standardDate":"2022-07-31","playedAt":"2022-07-31","playerName":"모토케이","playerRace":"T","playerUserId":"chs9011","opponentName":"토스봇","opponentRace":"P","map":"블루 스톰","elo":-15.1,"eloChange":-15.1,"matchType":"3/2(2)","memo":"2","result":"lose","isWin":false,"winnerPlayer":"토스봇","winnerName":"토스봇","winnerRace":"P","losePlayer":"모토케이","loseName":"모토케이","loseRace":"T","winnerSoopUserId":"","winnerUserId":"","loseSoopUserId":"chs9011","loserSoopUserId":"chs9011","loseUserId":"chs9011","loserUserId":"chs9011"},{"id":"chs9011_2022-07-31_토스봇_P_폴리포이드_18.6_3/2(1)_1","date":"2022-07-31","standardDate":"2022-07-31","playedAt":"2022-07-31","playerName":"모토케이","playerRace":"T","playerUserId":"chs9011","opponentName":"토스봇","opponentRace":"P","map":"폴리포이드","elo":18.6,"eloChange":18.6,"matchType":"3/2(1)","memo":"1","result":"win","isWin":true,"winnerPlayer":"모토케이","winnerName":"모토케이","winnerRace":"T","losePlayer":"토스봇","loseName":"토스봇","loseRace":"P","winnerSoopUserId":"chs9011","winnerUserId":"chs9011","loseSoopUserId":"","loserSoopUserId":"","loseUserId":"","loserUserId":""},{"id":"chs9011_2022-07-25_서현_P_블루_스톰_-12.1_3/2(3)_ㄴ","date":"2022-07-25","standardDate":"2022-07-25","playedAt":"2022-07-25","playerName":"모토케이","playerRace":"T","playerUserId":"chs9011","opponentName":"서현","opponentRace":"P","map":"블루 스톰","elo":-12.1,"eloChange":-12.1,"matchType":"3/2(3)","memo":"ㄴ","result":"lose","isWin":false,"winnerPlayer":"서현","winnerName":"서현","winnerRace":"P","losePlayer":"모토케이","loseName":"모토케이","loseRace":"T","winnerSoopUserId":"","winnerUserId":"","loseSoopUserId":"chs9011","loserSoopUserId":"chs9011","loseUserId":"chs9011","loserUserId":"chs9011"},{"id":"chs9011_2022-07-25_서현_P_네오실피드_-13.3_3/2(2)_ㅇ","date":"2022-07-25","standardDate":"2022-07-25","playedAt":"2022-07-25","playerName":"모토케이","playerRace":"T","playerUserId":"chs9011","opponentName":"서현","opponentRace":"P","map":"네오실피드","elo":-13.3,"eloChange":-13.3,"matchType":"3/2(2)","memo":"ㅇ","result":"lose","isWin":false,"winnerPlayer":"서현","winnerName":"서현","winnerRace":"P","losePlayer":"모토케이","loseName":"모토케이","loseRace":"T","winnerSoopUserId":"","winnerUserId":"","loseSoopUserId":"chs9011","loserSoopUserId":"chs9011","loseUserId":"chs9011","loserUserId":"chs9011"},{"id":"chs9011_2022-07-25_서현_P_블루_스톰_20.5_3/2(1)_ㅇ","date":"2022-07-25","standardDate":"2022-07-25","playedAt":"2022-07-25","playerName":"모토케이","playerRace":"T","playerUserId":"chs9011","opponentName":"서현","opponentRace":"P","map":"블루 스톰","elo":20.5,"eloChange":20.5,"matchType":"3/2(1)","memo":"ㅇ","result":"win","isWin":true,"winnerPlayer":"모토케이","winnerName":"모토케이","winnerRace":"T","losePlayer":"서현","loseName":"서현","loseRace":"P","winnerSoopUserId":"chs9011","winnerUserId":"chs9011","loseSoopUserId":"","loserSoopUserId":"","loseUserId":"","loserUserId":""},{"id":"chs9011_2022-07-24_수입뿌드_P_네오실피드_-16.1_3/2(3)_3","date":"2022-07-24","standardDate":"2022-07-24","playedAt":"2022-07-24","playerName":"모토케이","playerRace":"T","playerUserId":"chs9011","opponentName":"수입뿌드","opponentRace":"P","map":"네오실피드","elo":-16.1,"eloChange":-16.1,"matchType":"3/2(3)","memo":"3","result":"lose","isWin":false,"winnerPlayer":"수입뿌드","winnerName":"수입뿌드","winnerRace":"P","losePlayer":"모토케이","loseName":"모토케이","loseRace":"T","winnerSoopUserId":"","winnerUserId":"","loseSoopUserId":"chs9011","loserSoopUserId":"chs9011","loseUserId":"chs9011","loserUserId":"chs9011"},{"id":"chs9011_2022-07-24_수입뿌드_P_블루_스톰_17.5_3/2(2)_2","date":"2022-07-24","standardDate":"2022-07-24","playedAt":"2022-07-24","playerName":"모토케이","playerRace":"T","playerUserId":"chs9011","opponentName":"수입뿌드","opponentRace":"P","map":"블루 스톰","elo":17.5,"eloChange":17.5,"matchType":"3/2(2)","memo":"2","result":"win","isWin":true,"winnerPlayer":"모토케이","winnerName":"모토케이","winnerRace":"T","losePlayer":"수입뿌드","loseName":"수입뿌드","loseRace":"P","winnerSoopUserId":"chs9011","winnerUserId":"chs9011","loseSoopUserId":"","loserSoopUserId":"","loseUserId":"","loserUserId":""},{"id":"chs9011_2022-07-24_수입뿌드_P_폴리포이드_-15.9_3/2(1)_1","date":"2022-07-24","standardDate":"2022-07-24","playedAt":"2022-07-24","playerName":"모토케이","playerRace":"T","playerUserId":"chs9011","opponentName":"수입뿌드","opponentRace":"P","map":"폴리포이드","elo":-15.9,"eloChange":-15.9,"matchType":"3/2(1)","memo":"1","result":"lose","isWin":false,"winnerPlayer":"수입뿌드","winnerName":"수입뿌드","winnerRace":"P","losePlayer":"모토케이","loseName":"모토케이","loseRace":"T","winnerSoopUserId":"","winnerUserId":"","loseSoopUserId":"chs9011","loserSoopUserId":"chs9011","loseUserId":"chs9011","loserUserId":"chs9011"},{"id":"chs9011_2022-07-22_채린쟝_Z_네오실피드_22.2_3/2(3)_1","date":"2022-07-22","standardDate":"2022-07-22","playedAt":"2022-07-22","playerName":"모토케이","playerRace":"T","playerUserId":"chs9011","opponentName":"채린쟝","opponentRace":"Z","map":"네오실피드","elo":22.2,"eloChange":22.2,"matchType":"3/2(3)","memo":"1","result":"win","isWin":true,"winnerPlayer":"모토케이","winnerName":"모토케이","winnerRace":"T","losePlayer":"채린쟝","loseName":"채린쟝","loseRace":"Z","winnerSoopUserId":"chs9011","winnerUserId":"chs9011","loseSoopUserId":"","loserSoopUserId":"","loseUserId":"","loserUserId":""},{"id":"chs9011_2022-07-22_채린쟝_Z_블루_스톰_24_3/2(2)_1","date":"2022-07-22","standardDate":"2022-07-22","playedAt":"2022-07-22","playerName":"모토케이","playerRace":"T","playerUserId":"chs9011","opponentName":"채린쟝","opponentRace":"Z","map":"블루 스톰","elo":24,"eloChange":24,"matchType":"3/2(2)","memo":"1","result":"win","isWin":true,"winnerPlayer":"모토케이","winnerName":"모토케이","winnerRace":"T","losePlayer":"채린쟝","loseName":"채린쟝","loseRace":"Z","winnerSoopUserId":"chs9011","winnerUserId":"chs9011","loseSoopUserId":"","loserSoopUserId":"","loseUserId":"","loserUserId":""},{"id":"chs9011_2022-07-22_채린쟝_Z_폴리포이드_-8.6_3/2(1)_1","date":"2022-07-22","standardDate":"2022-07-22","playedAt":"2022-07-22","playerName":"모토케이","playerRace":"T","playerUserId":"chs9011","opponentName":"채린쟝","opponentRace":"Z","map":"폴리포이드","elo":-8.6,"eloChange":-8.6,"matchType":"3/2(1)","memo":"1","result":"lose","isWin":false,"winnerPlayer":"채린쟝","winnerName":"채린쟝","winnerRace":"Z","losePlayer":"모토케이","loseName":"모토케이","loseRace":"T","winnerSoopUserId":"","winnerUserId":"","loseSoopUserId":"chs9011","loserSoopUserId":"chs9011","loseUserId":"chs9011","loserUserId":"chs9011"},{"id":"chs9011_2022-07-22_토스봇_P_네오실피드_-13_단판_..","date":"2022-07-22","standardDate":"2022-07-22","playedAt":"2022-07-22","playerName":"모토케이","playerRace":"T","playerUserId":"chs9011","opponentName":"토스봇","opponentRace":"P","map":"네오실피드","elo":-13,"eloChange":-13,"matchType":"단판","memo":"..","result":"lose","isWin":false,"winnerPlayer":"토스봇","winnerName":"토스봇","winnerRace":"P","losePlayer":"모토케이","loseName":"모토케이","loseRace":"T","winnerSoopUserId":"","winnerUserId":"","loseSoopUserId":"chs9011","loserSoopUserId":"chs9011","loseUserId":"chs9011","loserUserId":"chs9011"},{"id":"chs9011_2022-07-22_토스봇_P_블루_스톰_20.8_단판_..","date":"2022-07-22","standardDate":"2022-07-22","playedAt":"2022-07-22","playerName":"모토케이","playerRace":"T","playerUserId":"chs9011","opponentName":"토스봇","opponentRace":"P","map":"블루 스톰","elo":20.8,"eloChange":20.8,"matchType":"단판","memo":"..","result":"win","isWin":true,"winnerPlayer":"모토케이","winnerName":"모토케이","winnerRace":"T","losePlayer":"토스봇","loseName":"토스봇","loseRace":"P","winnerSoopUserId":"chs9011","winnerUserId":"chs9011","loseSoopUserId":"","loserSoopUserId":"","loseUserId":"","loserUserId":""},{"id":"chs9011_2022-07-22_토스봇_P_폴리포이드_-12.3_단판_..","date":"2022-07-22","standardDate":"2022-07-22","playedAt":"2022-07-22","playerName":"모토케이","playerRace":"T","playerUserId":"chs9011","opponentName":"토스봇","opponentRace":"P","map":"폴리포이드","elo":-12.3,"eloChange":-12.3,"matchType":"단판","memo":"..","result":"lose","isWin":false,"winnerPlayer":"토스봇","winnerName":"토스봇","winnerRace":"P","losePlayer":"모토케이","loseName":"모토케이","loseRace":"T","winnerSoopUserId":"","winnerUserId":"","loseSoopUserId":"chs9011","loserSoopUserId":"chs9011","loseUserId":"chs9011","loserUserId":"chs9011"},{"id":"chs9011_2022-07-22_카덴지_Z_네오실피드_-12.8_3/2(3)_3","date":"2022-07-22","standardDate":"2022-07-22","playedAt":"2022-07-22","playerName":"모토케이","playerRace":"T","playerUserId":"chs9011","opponentName":"카덴지","opponentRace":"Z","map":"네오실피드","elo":-12.8,"eloChange":-12.8,"matchType":"3/2(3)","memo":"3","result":"lose","isWin":false,"winnerPlayer":"카덴지","winnerName":"카덴지","winnerRace":"Z","losePlayer":"모토케이","loseName":"모토케이","loseRace":"T","winnerSoopUserId":"","winnerUserId":"","loseSoopUserId":"chs9011","loserSoopUserId":"chs9011","loseUserId":"chs9011","loserUserId":"chs9011"},{"id":"chs9011_2022-07-22_카덴지_Z_블루_스톰_21_3/2(2)_2","date":"2022-07-22","standardDate":"2022-07-22","playedAt":"2022-07-22","playerName":"모토케이","playerRace":"T","playerUserId":"chs9011","opponentName":"카덴지","opponentRace":"Z","map":"블루 스톰","elo":21,"eloChange":21,"matchType":"3/2(2)","memo":"2","result":"win","isWin":true,"winnerPlayer":"모토케이","winnerName":"모토케이","winnerRace":"T","losePlayer":"카덴지","loseName":"카덴지","loseRace":"Z","winnerSoopUserId":"chs9011","winnerUserId":"chs9011","loseSoopUserId":"","loserSoopUserId":"","loseUserId":"","loserUserId":""},{"id":"chs9011_2022-07-22_카덴지_Z_폴리포이드_-12_3/2(1)_1","date":"2022-07-22","standardDate":"2022-07-22","playedAt":"2022-07-22","playerName":"모토케이","playerRace":"T","playerUserId":"chs9011","opponentName":"카덴지","opponentRace":"Z","map":"폴리포이드","elo":-12,"eloChange":-12,"matchType":"3/2(1)","memo":"1","result":"lose","isWin":false,"winnerPlayer":"카덴지","winnerName":"카덴지","winnerRace":"Z","losePlayer":"모토케이","loseName":"모토케이","loseRace":"T","winnerSoopUserId":"","winnerUserId":"","loseSoopUserId":"chs9011","loserSoopUserId":"chs9011","loseUserId":"chs9011","loserUserId":"chs9011"},{"id":"chs9011_2022-07-21_트슈_P_블루_스톰_-6.7_단판_1","date":"2022-07-21","standardDate":"2022-07-21","playedAt":"2022-07-21","playerName":"모토케이","playerRace":"T","playerUserId":"chs9011","opponentName":"트슈","opponentRace":"P","map":"블루 스톰","elo":-6.7,"eloChange":-6.7,"matchType":"단판","memo":"1","result":"lose","isWin":false,"winnerPlayer":"트슈","winnerName":"트슈","winnerRace":"P","losePlayer":"모토케이","loseName":"모토케이","loseRace":"T","winnerSoopUserId":"","winnerUserId":"","loseSoopUserId":"chs9011","loserSoopUserId":"chs9011","loseUserId":"chs9011","loserUserId":"chs9011"},{"id":"chs9011_2022-07-21_트슈_P_네오실피드_-7.1_단판_1","date":"2022-07-21","standardDate":"2022-07-21","playedAt":"2022-07-21","playerName":"모토케이","playerRace":"T","playerUserId":"chs9011","opponentName":"트슈","opponentRace":"P","map":"네오실피드","elo":-7.1,"eloChange":-7.1,"matchType":"단판","memo":"1","result":"lose","isWin":false,"winnerPlayer":"트슈","winnerName":"트슈","winnerRace":"P","losePlayer":"모토케이","loseName":"모토케이","loseRace":"T","winnerSoopUserId":"","winnerUserId":"","loseSoopUserId":"chs9011","loserSoopUserId":"chs9011","loseUserId":"chs9011","loserUserId":"chs9011"},{"id":"chs9011_2022-07-21_트슈_P_폴리포이드_-7.6_단판_1","date":"2022-07-21","standardDate":"2022-07-21","playedAt":"2022-07-21","playerName":"모토케이","playerRace":"T","playerUserId":"chs9011","opponentName":"트슈","opponentRace":"P","map":"폴리포이드","elo":-7.6,"eloChange":-7.6,"matchType":"단판","memo":"1","result":"lose","isWin":false,"winnerPlayer":"트슈","winnerName":"트슈","winnerRace":"P","losePlayer":"모토케이","loseName":"모토케이","loseRace":"T","winnerSoopUserId":"","winnerUserId":"","loseSoopUserId":"chs9011","loserSoopUserId":"chs9011","loseUserId":"chs9011","loserUserId":"chs9011"},{"id":"chs9011_2022-07-20_서도일_Z_폴리포이드_16.6_단판_리리스폰_단판","date":"2022-07-20","standardDate":"2022-07-20","playedAt":"2022-07-20","playerName":"모토케이","playerRace":"T","playerUserId":"chs9011","opponentName":"서도일","opponentRace":"Z","map":"폴리포이드","elo":16.6,"eloChange":16.6,"matchType":"단판","memo":"리리스폰 단판","result":"win","isWin":true,"winnerPlayer":"모토케이","winnerName":"모토케이","winnerRace":"T","losePlayer":"서도일","loseName":"서도일","loseRace":"Z","winnerSoopUserId":"chs9011","winnerUserId":"chs9011","loseSoopUserId":"","loserSoopUserId":"","loseUserId":"","loserUserId":""},{"id":"chs9011_2022-07-20_서도일_Z_투혼_-16.9_3/2(2)_리스폰_2","date":"2022-07-20","standardDate":"2022-07-20","playedAt":"2022-07-20","playerName":"모토케이","playerRace":"T","playerUserId":"chs9011","opponentName":"서도일","opponentRace":"Z","map":"투혼","elo":-16.9,"eloChange":-16.9,"matchType":"3/2(2)","memo":"리스폰 2","result":"lose","isWin":false,"winnerPlayer":"서도일","winnerName":"서도일","winnerRace":"Z","losePlayer":"모토케이","loseName":"모토케이","loseRace":"T","winnerSoopUserId":"","winnerUserId":"","loseSoopUserId":"chs9011","loserSoopUserId":"chs9011","loseUserId":"chs9011","loserUserId":"chs9011"},{"id":"chs9011_2022-07-20_서도일_Z_폴리포이드_-18.6_3/2(1)_리스폰_1","date":"2022-07-20","standardDate":"2022-07-20","playedAt":"2022-07-20","playerName":"모토케이","playerRace":"T","playerUserId":"chs9011","opponentName":"서도일","opponentRace":"Z","map":"폴리포이드","elo":-18.6,"eloChange":-18.6,"matchType":"3/2(1)","memo":"리스폰 1","result":"lose","isWin":false,"winnerPlayer":"서도일","winnerName":"서도일","winnerRace":"Z","losePlayer":"모토케이","loseName":"모토케이","loseRace":"T","winnerSoopUserId":"","winnerUserId":"","loseSoopUserId":"chs9011","loserSoopUserId":"chs9011","loseUserId":"chs9011","loserUserId":"chs9011"},{"id":"chs9011_2022-07-20_서도일_Z_폴리포이드_14.7_3/2(2)_2","date":"2022-07-20","standardDate":"2022-07-20","playedAt":"2022-07-20","playerName":"모토케이","playerRace":"T","playerUserId":"chs9011","opponentName":"서도일","opponentRace":"Z","map":"폴리포이드","elo":14.7,"eloChange":14.7,"matchType":"3/2(2)","memo":"2","result":"win","isWin":true,"winnerPlayer":"모토케이","winnerName":"모토케이","winnerRace":"T","losePlayer":"서도일","loseName":"서도일","loseRace":"Z","winnerSoopUserId":"chs9011","winnerUserId":"chs9011","loseSoopUserId":"","loserSoopUserId":"","loseUserId":"","loserUserId":""},{"id":"chs9011_2022-07-20_서도일_Z_이클립스_16.2_3/2(1)_1","date":"2022-07-20","standardDate":"2022-07-20","playedAt":"2022-07-20","playerName":"모토케이","playerRace":"T","playerUserId":"chs9011","opponentName":"서도일","opponentRace":"Z","map":"이클립스","elo":16.2,"eloChange":16.2,"matchType":"3/2(1)","memo":"1","result":"win","isWin":true,"winnerPlayer":"모토케이","winnerName":"모토케이","winnerRace":"T","losePlayer":"서도일","loseName":"서도일","loseRace":"Z","winnerSoopUserId":"chs9011","winnerUserId":"chs9011","loseSoopUserId":"","loserSoopUserId":"","loseUserId":"","loserUserId":""},{"id":"chs9011_2022-07-18_트슈_P_폴리포이드_-11.2_단판_JSA_학생테스트_점검","date":"2022-07-18","standardDate":"2022-07-18","playedAt":"2022-07-18","playerName":"모토케이","playerRace":"T","playerUserId":"chs9011","opponentName":"트슈","opponentRace":"P","map":"폴리포이드","elo":-11.2,"eloChange":-11.2,"matchType":"단판","memo":"JSA 학생테스트 점검","result":"lose","isWin":false,"winnerPlayer":"트슈","winnerName":"트슈","winnerRace":"P","losePlayer":"모토케이","loseName":"모토케이","loseRace":"T","winnerSoopUserId":"","winnerUserId":"","loseSoopUserId":"chs9011","loserSoopUserId":"chs9011","loseUserId":"chs9011","loserUserId":"chs9011"},{"id":"chs9011_2022-07-12_탱크_P_폴리포이드_-12.8_3/2(3)_.","date":"2022-07-12","standardDate":"2022-07-12","playedAt":"2022-07-12","playerName":"모토케이","playerRace":"T","playerUserId":"chs9011","opponentName":"탱크","opponentRace":"P","map":"폴리포이드","elo":-12.8,"eloChange":-12.8,"matchType":"3/2(3)","memo":".","result":"lose","isWin":false,"winnerPlayer":"탱크","winnerName":"탱크","winnerRace":"P","losePlayer":"모토케이","loseName":"모토케이","loseRace":"T","winnerSoopUserId":"","winnerUserId":"","loseSoopUserId":"chs9011","loserSoopUserId":"chs9011","loseUserId":"chs9011","loserUserId":"chs9011"},{"id":"chs9011_2022-07-12_탱크_P_폴리포이드_21_3/2(2)_.","date":"2022-07-12","standardDate":"2022-07-12","playedAt":"2022-07-12","playerName":"모토케이","playerRace":"T","playerUserId":"chs9011","opponentName":"탱크","opponentRace":"P","map":"폴리포이드","elo":21,"eloChange":21,"matchType":"3/2(2)","memo":".","result":"win","isWin":true,"winnerPlayer":"모토케이","winnerName":"모토케이","winnerRace":"T","losePlayer":"탱크","loseName":"탱크","loseRace":"P","winnerSoopUserId":"chs9011","winnerUserId":"chs9011","loseSoopUserId":"","loserSoopUserId":"","loseUserId":"","loserUserId":""},{"id":"chs9011_2022-07-12_탱크_P_폴리포이드_-12_3/2(1)_.","date":"2022-07-12","standardDate":"2022-07-12","playedAt":"2022-07-12","playerName":"모토케이","playerRace":"T","playerUserId":"chs9011","opponentName":"탱크","opponentRace":"P","map":"폴리포이드","elo":-12,"eloChange":-12,"matchType":"3/2(1)","memo":".","result":"lose","isWin":false,"winnerPlayer":"탱크","winnerName":"탱크","winnerRace":"P","losePlayer":"모토케이","loseName":"모토케이","loseRace":"T","winnerSoopUserId":"","winnerUserId":"","loseSoopUserId":"chs9011","loserSoopUserId":"chs9011","loseUserId":"chs9011","loserUserId":"chs9011"},{"id":"chs9011_2022-07-11_트슈_P_폴리포이드_22.2_3/2(2)_.","date":"2022-07-11","standardDate":"2022-07-11","playedAt":"2022-07-11","playerName":"모토케이","playerRace":"T","playerUserId":"chs9011","opponentName":"트슈","opponentRace":"P","map":"폴리포이드","elo":22.2,"eloChange":22.2,"matchType":"3/2(2)","memo":".","result":"win","isWin":true,"winnerPlayer":"모토케이","winnerName":"모토케이","winnerRace":"T","losePlayer":"트슈","loseName":"트슈","loseRace":"P","winnerSoopUserId":"chs9011","winnerUserId":"chs9011","loseSoopUserId":"","loserSoopUserId":"","loseUserId":"","loserUserId":""},{"id":"chs9011_2022-07-11_트슈_P_폴리포이드_-10.7_3/2(1)_.","date":"2022-07-11","standardDate":"2022-07-11","playedAt":"2022-07-11","playerName":"모토케이","playerRace":"T","playerUserId":"chs9011","opponentName":"트슈","opponentRace":"P","map":"폴리포이드","elo":-10.7,"eloChange":-10.7,"matchType":"3/2(1)","memo":".","result":"lose","isWin":false,"winnerPlayer":"트슈","winnerName":"트슈","winnerRace":"P","losePlayer":"모토케이","loseName":"모토케이","loseRace":"T","winnerSoopUserId":"","winnerUserId":"","loseSoopUserId":"chs9011","loserSoopUserId":"chs9011","loseUserId":"chs9011","loserUserId":"chs9011"},{"id":"chs9011_2022-07-11_탱크_P_폴리포이드_22.1_3/2(2)_.","date":"2022-07-11","standardDate":"2022-07-11","playedAt":"2022-07-11","playerName":"모토케이","playerRace":"T","playerUserId":"chs9011","opponentName":"탱크","opponentRace":"P","map":"폴리포이드","elo":22.1,"eloChange":22.1,"matchType":"3/2(2)","memo":".","result":"win","isWin":true,"winnerPlayer":"모토케이","winnerName":"모토케이","winnerRace":"T","losePlayer":"탱크","loseName":"탱크","loseRace":"P","winnerSoopUserId":"chs9011","winnerUserId":"chs9011","loseSoopUserId":"","loserSoopUserId":"","loseUserId":"","loserUserId":""},{"id":"chs9011_2022-07-11_탱크_P_폴리포이드_23.9_3/2(1)_.","date":"2022-07-11","standardDate":"2022-07-11","playedAt":"2022-07-11","playerName":"모토케이","playerRace":"T","playerUserId":"chs9011","opponentName":"탱크","opponentRace":"P","map":"폴리포이드","elo":23.9,"eloChange":23.9,"matchType":"3/2(1)","memo":".","result":"win","isWin":true,"winnerPlayer":"모토케이","winnerName":"모토케이","winnerRace":"T","losePlayer":"탱크","loseName":"탱크","loseRace":"P","winnerSoopUserId":"chs9011","winnerUserId":"chs9011","loseSoopUserId":"","loserSoopUserId":"","loseUserId":"","loserUserId":""},{"id":"chs9011_2022-07-11_트슈_P_폴리포이드_-11.6_3/2(3)_.","date":"2022-07-11","standardDate":"2022-07-11","playedAt":"2022-07-11","playerName":"모토케이","playerRace":"T","playerUserId":"chs9011","opponentName":"트슈","opponentRace":"P","map":"폴리포이드","elo":-11.6,"eloChange":-11.6,"matchType":"3/2(3)","memo":".","result":"lose","isWin":false,"winnerPlayer":"트슈","winnerName":"트슈","winnerRace":"P","losePlayer":"모토케이","loseName":"모토케이","loseRace":"T","winnerSoopUserId":"","winnerUserId":"","loseSoopUserId":"chs9011","loserSoopUserId":"chs9011","loseUserId":"chs9011","loserUserId":"chs9011"},{"id":"chs9011_2022-07-07_수입뿌드_P_투혼_-14.5_3/2(2)_3/2_2경기","date":"2022-07-07","standardDate":"2022-07-07","playedAt":"2022-07-07","playerName":"모토케이","playerRace":"T","playerUserId":"chs9011","opponentName":"수입뿌드","opponentRace":"P","map":"투혼","elo":-14.5,"eloChange":-14.5,"matchType":"3/2(2)","memo":"3/2 2경기","result":"lose","isWin":false,"winnerPlayer":"수입뿌드","winnerName":"수입뿌드","winnerRace":"P","losePlayer":"모토케이","loseName":"모토케이","loseRace":"T","winnerSoopUserId":"","winnerUserId":"","loseSoopUserId":"chs9011","loserSoopUserId":"chs9011","loseUserId":"chs9011","loserUserId":"chs9011"},{"id":"chs9011_2022-07-07_수입뿌드_P_폴리포이드_-15.9_3/2(1)_3/2_1경기","date":"2022-07-07","standardDate":"2022-07-07","playedAt":"2022-07-07","playerName":"모토케이","playerRace":"T","playerUserId":"chs9011","opponentName":"수입뿌드","opponentRace":"P","map":"폴리포이드","elo":-15.9,"eloChange":-15.9,"matchType":"3/2(1)","memo":"3/2 1경기","result":"lose","isWin":false,"winnerPlayer":"수입뿌드","winnerName":"수입뿌드","winnerRace":"P","losePlayer":"모토케이","loseName":"모토케이","loseRace":"T","winnerSoopUserId":"","winnerUserId":"","loseSoopUserId":"chs9011","loserSoopUserId":"chs9011","loseUserId":"chs9011","loserUserId":"chs9011"},{"id":"chs9011_2022-07-05_서도일_Z_라르고_-16.9_단판_단판","date":"2022-07-05","standardDate":"2022-07-05","playedAt":"2022-07-05","playerName":"모토케이","playerRace":"T","playerUserId":"chs9011","opponentName":"서도일","opponentRace":"Z","map":"라르고","elo":-16.9,"eloChange":-16.9,"matchType":"단판","memo":"단판","result":"lose","isWin":false,"winnerPlayer":"서도일","winnerName":"서도일","winnerRace":"Z","losePlayer":"모토케이","loseName":"모토케이","loseRace":"T","winnerSoopUserId":"","winnerUserId":"","loseSoopUserId":"chs9011","loserSoopUserId":"chs9011","loseUserId":"chs9011","loserUserId":"chs9011"}]