[{"id":"dbrbals_2026-06-29_전태규_P_폴리포이드_14.5_7/4(4)_뉴캄옥션_스크림_윤열팀_vs_태규팀(4)","date":"2026-06-29","standardDate":"2026-06-29","playedAt":"2026-06-29","playerName":"초난강","playerRace":"T","playerUserId":"dbrbals","opponentName":"전태규","opponentRace":"P","map":"폴리포이드","elo":14.5,"eloChange":14.5,"matchType":"7/4(4)","memo":"뉴캄옥션 스크림 윤열팀 vs 태규팀(4)","result":"win","isWin":true,"winnerPlayer":"초난강","winnerName":"초난강","winnerRace":"T","losePlayer":"전태규","loseName":"전태규","loseRace":"P","winnerSoopUserId":"dbrbals","winnerUserId":"dbrbals","loseSoopUserId":"","loserSoopUserId":"","loseUserId":"","loserUserId":""},{"date":"2026-05-14","elo":15.6,"eloChange":15.6,"id":"dbrbals_2026-05-14_박태민_Z_네오_실피드_15.6_11/6(2)_뉴캣슬_스승의날CK_(2)","isWin":true,"loseName":"박태민","losePlayer":"박태민","loseRace":"Z","loseSoopUserId":"","loseUserId":"","loserSoopUserId":"","loserUserId":"","map":"네오 실피드","matchType":"11/6(2)","memo":"뉴캣슬 스승의날CK (2)","opponentName":"박태민","opponentRace":"Z","playedAt":"2026-05-14","playerName":"초난강","playerRace":"T","playerUserId":"dbrbals","result":"win","standardDate":"2026-05-14","winnerName":"초난강","winnerPlayer":"초난강","winnerRace":"T","winnerSoopUserId":"dbrbals","winnerUserId":"dbrbals"},{"date":"2026-05-03","elo":-22.1,"eloChange":-22.1,"id":"dbrbals_2026-05-03_김봉준_P_네오_실피드_-22.1_9/5(1)_뉴캣슬_vs_무창클럽_스타대전_(1)","isWin":false,"loseName":"초난강","losePlayer":"초난강","loseRace":"T","loseSoopUserId":"dbrbals","loseUserId":"dbrbals","loserSoopUserId":"dbrbals","loserUserId":"dbrbals","map":"네오 실피드","matchType":"9/5(1)","memo":"뉴캣슬 vs 무창클럽 스타대전 (1)","opponentName":"김봉준","opponentRace":"P","playedAt":"2026-05-03","playerName":"초난강","playerRace":"T","playerUserId":"dbrbals","result":"lose","standardDate":"2026-05-03","winnerName":"김봉준","winnerPlayer":"김봉준","winnerRace":"P","winnerSoopUserId":"","winnerUserId":""}]