[{"id":"dbsdydx_2026-06-20_김태영_T_네오_실피드_21.9_3/2(2)_ㅅㅍ","date":"2026-06-20","standardDate":"2026-06-20","playedAt":"2026-06-20","playerName":"윤용태","playerRace":"P","playerUserId":"dbsdydx","opponentName":"김태영","opponentRace":"T","map":"네오 실피드","elo":21.9,"eloChange":21.9,"matchType":"3/2(2)","memo":"ㅅㅍ","result":"win","isWin":true,"winnerPlayer":"윤용태","winnerName":"윤용태","winnerRace":"P","losePlayer":"김태영","loseName":"김태영","loseRace":"T","winnerSoopUserId":"dbsdydx","winnerUserId":"dbsdydx","loseSoopUserId":"","loserSoopUserId":"","loseUserId":"","loserUserId":""},{"id":"dbsdydx_2026-06-20_김태영_T_옥타곤_23.6_3/2(1)_ㅅㅍ","date":"2026-06-20","standardDate":"2026-06-20","playedAt":"2026-06-20","playerName":"윤용태","playerRace":"P","playerUserId":"dbsdydx","opponentName":"김태영","opponentRace":"T","map":"옥타곤","elo":23.6,"eloChange":23.6,"matchType":"3/2(1)","memo":"ㅅㅍ","result":"win","isWin":true,"winnerPlayer":"윤용태","winnerName":"윤용태","winnerRace":"P","losePlayer":"김태영","loseName":"김태영","loseRace":"T","winnerSoopUserId":"dbsdydx","winnerUserId":"dbsdydx","loseSoopUserId":"","loserSoopUserId":"","loseUserId":"","loserUserId":""},{"id":"dbsdydx_2026-06-19_김윤환_Z_라데온_-17_9/5(9)_혼성리그_에이스_결정전","date":"2026-06-19","standardDate":"2026-06-19","playedAt":"2026-06-19","playerName":"윤용태","playerRace":"P","playerUserId":"dbsdydx","opponentName":"김윤환","opponentRace":"Z","map":"라데온","elo":-17,"eloChange":-17,"matchType":"9/5(9)","memo":"혼성리그 에이스 결정전","result":"lose","isWin":false,"winnerPlayer":"김윤환","winnerName":"김윤환","winnerRace":"Z","losePlayer":"윤용태","loseName":"윤용태","loseRace":"P","winnerSoopUserId":"","winnerUserId":"","loseSoopUserId":"dbsdydx","loserSoopUserId":"dbsdydx","loseUserId":"dbsdydx","loserUserId":"dbsdydx"},{"id":"dbsdydx_2026-06-19_김윤환_Z_라데온_-18.7_9/5(8)_혼성리그_(8)","date":"2026-06-19","standardDate":"2026-06-19","playedAt":"2026-06-19","playerName":"윤용태","playerRace":"P","playerUserId":"dbsdydx","opponentName":"김윤환","opponentRace":"Z","map":"라데온","elo":-18.7,"eloChange":-18.7,"matchType":"9/5(8)","memo":"혼성리그 (8)","result":"lose","isWin":false,"winnerPlayer":"김윤환","winnerName":"김윤환","winnerRace":"Z","losePlayer":"윤용태","loseName":"윤용태","loseRace":"P","winnerSoopUserId":"","winnerUserId":"","loseSoopUserId":"dbsdydx","loserSoopUserId":"dbsdydx","loseUserId":"dbsdydx","loserUserId":"dbsdydx"},{"id":"dbsdydx_2026-06-19_김윤환_Z_라데온_-20.5_9/5(2)_혼성리그_(2)","date":"2026-06-19","standardDate":"2026-06-19","playedAt":"2026-06-19","playerName":"윤용태","playerRace":"P","playerUserId":"dbsdydx","opponentName":"김윤환","opponentRace":"Z","map":"라데온","elo":-20.5,"eloChange":-20.5,"matchType":"9/5(2)","memo":"혼성리그 (2)","result":"lose","isWin":false,"winnerPlayer":"김윤환","winnerName":"김윤환","winnerRace":"Z","losePlayer":"윤용태","loseName":"윤용태","loseRace":"P","winnerSoopUserId":"","winnerUserId":"","loseSoopUserId":"dbsdydx","loserSoopUserId":"dbsdydx","loseUserId":"dbsdydx","loserUserId":"dbsdydx"},{"date":"2026-06-17","elo":-13,"eloChange":-13,"id":"dbsdydx_2026-06-17_유승곤_T_네오_실피드_-13_7/4(5)_씨나인_2:2_끝장전_5경기","isWin":false,"loseName":"윤용태","losePlayer":"윤용태","loseRace":"P","loseSoopUserId":"dbsdydx","loseUserId":"dbsdydx","loserSoopUserId":"dbsdydx","loserUserId":"dbsdydx","map":"네오 실피드","matchType":"7/4(5)","memo":"씨나인 2:2 끝장전 5경기","opponentName":"유승곤","opponentRace":"T","playedAt":"2026-06-17","playerName":"윤용태","playerRace":"P","playerUserId":"dbsdydx","result":"lose","standardDate":"2026-06-17","winnerName":"유승곤","winnerPlayer":"유승곤","winnerRace":"T","winnerSoopUserId":"","winnerUserId":""},{"date":"2026-06-17","elo":20.8,"eloChange":20.8,"id":"dbsdydx_2026-06-17_유승곤_T_매치포인트_20.8_7/4(3)_씨나인_2:2_끝장전_3경기","isWin":true,"loseName":"유승곤","losePlayer":"유승곤","loseRace":"T","loseSoopUserId":"","loseUserId":"","loserSoopUserId":"","loserUserId":"","map":"매치포인트","matchType":"7/4(3)","memo":"씨나인 2:2 끝장전 3경기","opponentName":"유승곤","opponentRace":"T","playedAt":"2026-06-17","playerName":"윤용태","playerRace":"P","playerUserId":"dbsdydx","result":"win","standardDate":"2026-06-17","winnerName":"윤용태","winnerPlayer":"윤용태","winnerRace":"P","winnerSoopUserId":"dbsdydx","winnerUserId":"dbsdydx"},{"date":"2026-06-17","elo":-12.3,"eloChange":-12.3,"id":"dbsdydx_2026-06-17_유승곤_T_제인_도_-12.3_7/4(1)_씨나인_2:2_끝장전_1경기","isWin":false,"loseName":"윤용태","losePlayer":"윤용태","loseRace":"P","loseSoopUserId":"dbsdydx","loseUserId":"dbsdydx","loserSoopUserId":"dbsdydx","loserUserId":"dbsdydx","map":"제인 도","matchType":"7/4(1)","memo":"씨나인 2:2 끝장전 1경기","opponentName":"유승곤","opponentRace":"T","playedAt":"2026-06-17","playerName":"윤용태","playerRace":"P","playerUserId":"dbsdydx","result":"lose","standardDate":"2026-06-17","winnerName":"유승곤","winnerPlayer":"유승곤","winnerRace":"T","winnerSoopUserId":"","winnerUserId":""},{"date":"2026-06-17","elo":-11.2,"eloChange":-11.2,"id":"dbsdydx_2026-06-17_김태영_T_옥타곤_-11.2_3/2(3)_32","isWin":false,"loseName":"윤용태","losePlayer":"윤용태","loseRace":"P","loseSoopUserId":"dbsdydx","loseUserId":"dbsdydx","loserSoopUserId":"dbsdydx","loserUserId":"dbsdydx","map":"옥타곤","matchType":"3/2(3)","memo":"32","opponentName":"김태영","opponentRace":"T","playedAt":"2026-06-17","playerName":"윤용태","playerRace":"P","playerUserId":"dbsdydx","result":"lose","standardDate":"2026-06-17","winnerName":"김태영","winnerPlayer":"김태영","winnerRace":"T","winnerSoopUserId":"","winnerUserId":""},{"date":"2026-06-17","elo":-12.3,"eloChange":-12.3,"id":"dbsdydx_2026-06-17_김태영_T_네오_실피드_-12.3_3/2(2)_32","isWin":false,"loseName":"윤용태","losePlayer":"윤용태","loseRace":"P","loseSoopUserId":"dbsdydx","loseUserId":"dbsdydx","loserSoopUserId":"dbsdydx","loserUserId":"dbsdydx","map":"네오 실피드","matchType":"3/2(2)","memo":"32","opponentName":"김태영","opponentRace":"T","playedAt":"2026-06-17","playerName":"윤용태","playerRace":"P","playerUserId":"dbsdydx","result":"lose","standardDate":"2026-06-17","winnerName":"김태영","winnerPlayer":"김태영","winnerRace":"T","winnerSoopUserId":"","winnerUserId":""},{"date":"2026-06-17","elo":21.5,"eloChange":21.5,"id":"dbsdydx_2026-06-17_김태영_T_녹아웃_21.5_3/2(1)_32","isWin":true,"loseName":"김태영","losePlayer":"김태영","loseRace":"T","loseSoopUserId":"","loseUserId":"","loserSoopUserId":"","loserUserId":"","map":"녹아웃","matchType":"3/2(1)","memo":"32","opponentName":"김태영","opponentRace":"T","playedAt":"2026-06-17","playerName":"윤용태","playerRace":"P","playerUserId":"dbsdydx","result":"win","standardDate":"2026-06-17","winnerName":"윤용태","winnerPlayer":"윤용태","winnerRace":"P","winnerSoopUserId":"dbsdydx","winnerUserId":"dbsdydx"},{"date":"2026-05-08","elo":-8.3,"eloChange":-8.3,"id":"dbsdydx_2026-05-08_조일장_Z_옥타곤_-8.3_단판_E-SCORE_TOURNAMENT_S2_6주차_32강","isWin":false,"loseName":"윤용태","losePlayer":"윤용태","loseRace":"P","loseSoopUserId":"dbsdydx","loseUserId":"dbsdydx","loserSoopUserId":"dbsdydx","loserUserId":"dbsdydx","map":"옥타곤","matchType":"단판","memo":"E-SCORE TOURNAMENT S2 6주차 32강","opponentName":"조일장","opponentRace":"Z","playedAt":"2026-05-08","playerName":"윤용태","playerRace":"P","playerUserId":"dbsdydx","result":"lose","standardDate":"2026-05-08","winnerName":"조일장","winnerPlayer":"조일장","winnerRace":"Z","winnerSoopUserId":"","winnerUserId":""},{"date":"2026-05-08","elo":9.6,"eloChange":9.6,"id":"dbsdydx_2026-05-08_박재혁_Z_네오_실피드_9.6_단판_E-SCORE_TOURNAMENT_S2_6주차_64강","isWin":true,"loseName":"박재혁","losePlayer":"박재혁","loseRace":"Z","loseSoopUserId":"","loseUserId":"","loserSoopUserId":"","loserUserId":"","map":"네오 실피드","matchType":"단판","memo":"E-SCORE TOURNAMENT S2 6주차 64강","opponentName":"박재혁","opponentRace":"Z","playedAt":"2026-05-08","playerName":"윤용태","playerRace":"P","playerUserId":"dbsdydx","result":"win","standardDate":"2026-05-08","winnerName":"윤용태","winnerPlayer":"윤용태","winnerRace":"P","winnerSoopUserId":"dbsdydx","winnerUserId":"dbsdydx"},{"date":"2026-04-28","elo":-10,"eloChange":-10,"id":"dbsdydx_2026-04-28_김태영_T_폴스타_-10_단판_ㅅㅍ","isWin":false,"loseName":"윤용태","losePlayer":"윤용태","loseRace":"P","loseSoopUserId":"dbsdydx","loseUserId":"dbsdydx","loserSoopUserId":"dbsdydx","loserUserId":"dbsdydx","map":"폴스타","matchType":"단판","memo":"ㅅㅍ","opponentName":"김태영","opponentRace":"T","playedAt":"2026-04-28","playerName":"윤용태","playerRace":"P","playerUserId":"dbsdydx","result":"lose","standardDate":"2026-04-28","winnerName":"김태영","winnerPlayer":"김태영","winnerRace":"T","winnerSoopUserId":"","winnerUserId":""},{"date":"2026-04-28","elo":-10.9,"eloChange":-10.9,"id":"dbsdydx_2026-04-28_김태영_T_녹아웃_-10.9_단판_ㅅㅍ","isWin":false,"loseName":"윤용태","losePlayer":"윤용태","loseRace":"P","loseSoopUserId":"dbsdydx","loseUserId":"dbsdydx","loserSoopUserId":"dbsdydx","loserUserId":"dbsdydx","map":"녹아웃","matchType":"단판","memo":"ㅅㅍ","opponentName":"김태영","opponentRace":"T","playedAt":"2026-04-28","playerName":"윤용태","playerRace":"P","playerUserId":"dbsdydx","result":"lose","standardDate":"2026-04-28","winnerName":"김태영","winnerPlayer":"김태영","winnerRace":"T","winnerSoopUserId":"","winnerUserId":""},{"date":"2026-04-27","elo":-12.5,"eloChange":-12.5,"id":"dbsdydx_2026-04-27_김태영_T_제인_도_-12.5_5/3(1)_씨나인_즉흥_CK_1세트_1경기","isWin":false,"loseName":"윤용태","losePlayer":"윤용태","loseRace":"P","loseSoopUserId":"dbsdydx","loseUserId":"dbsdydx","loserSoopUserId":"dbsdydx","loserUserId":"dbsdydx","map":"제인 도","matchType":"5/3(1)","memo":"씨나인 즉흥 CK 1세트 1경기","opponentName":"김태영","opponentRace":"T","playedAt":"2026-04-27","playerName":"윤용태","playerRace":"P","playerUserId":"dbsdydx","result":"lose","standardDate":"2026-04-27","winnerName":"김태영","winnerPlayer":"김태영","winnerRace":"T","winnerSoopUserId":"","winnerUserId":""},{"date":"2026-04-25","elo":25.5,"eloChange":25.5,"id":"dbsdydx_2026-04-25_조기석_T_옥타곤_25.5_단판_윤용태_승","isWin":true,"loseName":"조기석","losePlayer":"조기석","loseRace":"T","loseSoopUserId":"","loseUserId":"","loserSoopUserId":"","loserUserId":"","map":"옥타곤","matchType":"단판","memo":"윤용태 승","opponentName":"조기석","opponentRace":"T","playedAt":"2026-04-25","playerName":"윤용태","playerRace":"P","playerUserId":"dbsdydx","result":"win","standardDate":"2026-04-25","winnerName":"윤용태","winnerPlayer":"윤용태","winnerRace":"P","winnerSoopUserId":"dbsdydx","winnerUserId":"dbsdydx"},{"date":"2026-04-24","elo":-6.4,"eloChange":-6.4,"id":"dbsdydx_2026-04-24_김지성_T_옥타곤_-6.4_단판_E-SCORE_TOURNAMENT_S2_4주차_32강","isWin":false,"loseName":"윤용태","losePlayer":"윤용태","loseRace":"P","loseSoopUserId":"dbsdydx","loseUserId":"dbsdydx","loserSoopUserId":"dbsdydx","loserUserId":"dbsdydx","map":"옥타곤","matchType":"단판","memo":"E-SCORE TOURNAMENT S2 4주차 32강","opponentName":"김지성","opponentRace":"T","playedAt":"2026-04-24","playerName":"윤용태","playerRace":"P","playerUserId":"dbsdydx","result":"lose","standardDate":"2026-04-24","winnerName":"김지성","winnerPlayer":"김지성","winnerRace":"T","winnerSoopUserId":"","winnerUserId":""},{"date":"2026-04-24","elo":9.7,"eloChange":9.7,"id":"dbsdydx_2026-04-24_허유진_Z_네오_실피드_9.7_단판_E-SCORE_TOURNAMENT_S2_4주차_64강","isWin":true,"loseName":"허유진","losePlayer":"허유진","loseRace":"Z","loseSoopUserId":"","loseUserId":"","loserSoopUserId":"","loserUserId":"","map":"네오 실피드","matchType":"단판","memo":"E-SCORE TOURNAMENT S2 4주차 64강","opponentName":"허유진","opponentRace":"Z","playedAt":"2026-04-24","playerName":"윤용태","playerRace":"P","playerUserId":"dbsdydx","result":"win","standardDate":"2026-04-24","winnerName":"윤용태","winnerPlayer":"윤용태","winnerRace":"P","winnerSoopUserId":"dbsdydx","winnerUserId":"dbsdydx"},{"date":"2026-04-17","elo":-4.2,"eloChange":-4.2,"id":"dbsdydx_2026-04-17_박상현_Z_옥타곤_-4.2_단판_E-SCORE_TOURNAMENT_S2_3주차_32강","isWin":false,"loseName":"윤용태","losePlayer":"윤용태","loseRace":"P","loseSoopUserId":"dbsdydx","loseUserId":"dbsdydx","loserSoopUserId":"dbsdydx","loserUserId":"dbsdydx","map":"옥타곤","matchType":"단판","memo":"E-SCORE TOURNAMENT S2 3주차 32강","opponentName":"박상현","opponentRace":"Z","playedAt":"2026-04-17","playerName":"윤용태","playerRace":"P","playerUserId":"dbsdydx","result":"lose","standardDate":"2026-04-17","winnerName":"박상현","winnerPlayer":"박상현","winnerRace":"Z","winnerSoopUserId":"","winnerUserId":""},{"date":"2026-04-17","elo":10.3,"eloChange":10.3,"id":"dbsdydx_2026-04-17_최재성_T_네오_실피드_10.3_단판_E-SCORE_TOURNAMENT_S2_3주차_64강","isWin":true,"loseName":"최재성","losePlayer":"최재성","loseRace":"T","loseSoopUserId":"","loseUserId":"","loserSoopUserId":"","loserUserId":"","map":"네오 실피드","matchType":"단판","memo":"E-SCORE TOURNAMENT S2 3주차 64강","opponentName":"최재성","opponentRace":"T","playedAt":"2026-04-17","playerName":"윤용태","playerRace":"P","playerUserId":"dbsdydx","result":"win","standardDate":"2026-04-17","winnerName":"윤용태","winnerPlayer":"윤용태","winnerRace":"P","winnerSoopUserId":"dbsdydx","winnerUserId":"dbsdydx"},{"date":"2026-04-09","elo":-7.9,"eloChange":-7.9,"id":"dbsdydx_2026-04-09_정영재_T_폴스타_-7.9_단판_1","isWin":false,"loseName":"윤용태","losePlayer":"윤용태","loseRace":"P","loseSoopUserId":"dbsdydx","loseUserId":"dbsdydx","loserSoopUserId":"dbsdydx","loserUserId":"dbsdydx","map":"폴스타","matchType":"단판","memo":"1","opponentName":"정영재","opponentRace":"T","playedAt":"2026-04-09","playerName":"윤용태","playerRace":"P","playerUserId":"dbsdydx","result":"lose","standardDate":"2026-04-09","winnerName":"정영재","winnerPlayer":"정영재","winnerRace":"T","winnerSoopUserId":"","winnerUserId":""},{"date":"2026-04-09","elo":-8.5,"eloChange":-8.5,"id":"dbsdydx_2026-04-09_정영재_T_녹아웃_-8.5_단판_1","isWin":false,"loseName":"윤용태","losePlayer":"윤용태","loseRace":"P","loseSoopUserId":"dbsdydx","loseUserId":"dbsdydx","loserSoopUserId":"dbsdydx","loserUserId":"dbsdydx","map":"녹아웃","matchType":"단판","memo":"1","opponentName":"정영재","opponentRace":"T","playedAt":"2026-04-09","playerName":"윤용태","playerRace":"P","playerUserId":"dbsdydx","result":"lose","standardDate":"2026-04-09","winnerName":"정영재","winnerPlayer":"정영재","winnerRace":"T","winnerSoopUserId":"","winnerUserId":""},{"date":"2026-04-09","elo":-11.8,"eloChange":-11.8,"id":"dbsdydx_2026-04-09_김태영_T_옥타곤_-11.8_9/5(5)_92즈CK_(5)","isWin":false,"loseName":"윤용태","losePlayer":"윤용태","loseRace":"P","loseSoopUserId":"dbsdydx","loseUserId":"dbsdydx","loserSoopUserId":"dbsdydx","loserUserId":"dbsdydx","map":"옥타곤","matchType":"9/5(5)","memo":"92즈CK (5)","opponentName":"김태영","opponentRace":"T","playedAt":"2026-04-09","playerName":"윤용태","playerRace":"P","playerUserId":"dbsdydx","result":"lose","standardDate":"2026-04-09","winnerName":"김태영","winnerPlayer":"김태영","winnerRace":"T","winnerSoopUserId":"","winnerUserId":""},{"date":"2026-04-07","elo":-16.3,"eloChange":-16.3,"id":"dbsdydx_2026-04-07_박준오_Z_옥타곤_-16.3_5/3(1)_츠캄_저그반CK_1세트_1경기","isWin":false,"loseName":"윤용태","losePlayer":"윤용태","loseRace":"P","loseSoopUserId":"dbsdydx","loseUserId":"dbsdydx","loserSoopUserId":"dbsdydx","loserUserId":"dbsdydx","map":"옥타곤","matchType":"5/3(1)","memo":"츠캄 저그반CK 1세트 1경기","opponentName":"박준오","opponentRace":"Z","playedAt":"2026-04-07","playerName":"윤용태","playerRace":"P","playerUserId":"dbsdydx","result":"lose","standardDate":"2026-04-07","winnerName":"박준오","winnerPlayer":"박준오","winnerRace":"Z","winnerSoopUserId":"","winnerUserId":""},{"date":"2026-04-05","elo":14.3,"eloChange":14.3,"id":"dbsdydx_2026-04-05_방태수_Z_매치포인트_14.3_단판_K리그_2세트_루저스_3경기","isWin":true,"loseName":"방태수","losePlayer":"방태수","loseRace":"Z","loseSoopUserId":"","loseUserId":"","loserSoopUserId":"","loserUserId":"","map":"매치포인트","matchType":"단판","memo":"K리그 2세트 루저스 3경기","opponentName":"방태수","opponentRace":"Z","playedAt":"2026-04-05","playerName":"윤용태","playerRace":"P","playerUserId":"dbsdydx","result":"win","standardDate":"2026-04-05","winnerName":"윤용태","winnerPlayer":"윤용태","winnerRace":"P","winnerSoopUserId":"dbsdydx","winnerUserId":"dbsdydx"},{"date":"2026-04-05","elo":-9,"eloChange":-9,"id":"dbsdydx_2026-04-05_황병영_T_네오_실피드_-9_단판_K리그_1세트_3경기","isWin":false,"loseName":"윤용태","losePlayer":"윤용태","loseRace":"P","loseSoopUserId":"dbsdydx","loseUserId":"dbsdydx","loserSoopUserId":"dbsdydx","loserUserId":"dbsdydx","map":"네오 실피드","matchType":"단판","memo":"K리그 1세트 3경기","opponentName":"황병영","opponentRace":"T","playedAt":"2026-04-05","playerName":"윤용태","playerRace":"P","playerUserId":"dbsdydx","result":"lose","standardDate":"2026-04-05","winnerName":"황병영","winnerPlayer":"황병영","winnerRace":"T","winnerSoopUserId":"","winnerUserId":""},{"date":"2026-03-24","elo":20.6,"eloChange":20.6,"id":"dbsdydx_2026-03-24_김재현_T_애티튜드_20.6_7/4(5)_4:4:4:4_킹/잭_팀배틀_4강_B조_5경기","isWin":true,"loseName":"김재현","losePlayer":"김재현","loseRace":"T","loseSoopUserId":"","loseUserId":"","loserSoopUserId":"","loserUserId":"","map":"애티튜드","matchType":"7/4(5)","memo":"4:4:4:4 킹/잭 팀배틀 4강 B조 5경기","opponentName":"김재현","opponentRace":"T","playedAt":"2026-03-24","playerName":"윤용태","playerRace":"P","playerUserId":"dbsdydx","result":"win","standardDate":"2026-03-24","winnerName":"윤용태","winnerPlayer":"윤용태","winnerRace":"P","winnerSoopUserId":"dbsdydx","winnerUserId":"dbsdydx"},{"date":"2026-03-24","elo":14,"eloChange":14,"id":"dbsdydx_2026-03-24_지동원_T_네오_실피드_14_7/4(4)_4:4:4:4_킹/잭_팀배틀_4강_B조_4경기","isWin":true,"loseName":"지동원","losePlayer":"지동원","loseRace":"T","loseSoopUserId":"","loseUserId":"","loserSoopUserId":"","loserUserId":"","map":"네오 실피드","matchType":"7/4(4)","memo":"4:4:4:4 킹/잭 팀배틀 4강 B조 4경기","opponentName":"지동원","opponentRace":"T","playedAt":"2026-03-24","playerName":"윤용태","playerRace":"P","playerUserId":"dbsdydx","result":"win","standardDate":"2026-03-24","winnerName":"윤용태","winnerPlayer":"윤용태","winnerRace":"P","winnerSoopUserId":"dbsdydx","winnerUserId":"dbsdydx"},{"date":"2026-03-23","elo":-14.7,"eloChange":-14.7,"id":"dbsdydx_2026-03-23_신상문_T_애티튜드_-14.7_단판_김윤환배_잭티어_월드컵_그룹A_13강","isWin":false,"loseName":"윤용태","losePlayer":"윤용태","loseRace":"P","loseSoopUserId":"dbsdydx","loseUserId":"dbsdydx","loserSoopUserId":"dbsdydx","loserUserId":"dbsdydx","map":"애티튜드","matchType":"단판","memo":"김윤환배 잭티어 월드컵 그룹A 13강","opponentName":"신상문","opponentRace":"T","playedAt":"2026-03-23","playerName":"윤용태","playerRace":"P","playerUserId":"dbsdydx","result":"lose","standardDate":"2026-03-23","winnerName":"신상문","winnerPlayer":"신상문","winnerRace":"T","winnerSoopUserId":"","winnerUserId":""},{"date":"2026-03-15","elo":-10.8,"eloChange":-10.8,"id":"dbsdydx_2026-03-15_김윤중_P_폴스타_-10.8_단판_단판","isWin":false,"loseName":"윤용태","losePlayer":"윤용태","loseRace":"P","loseSoopUserId":"dbsdydx","loseUserId":"dbsdydx","loserSoopUserId":"dbsdydx","loserUserId":"dbsdydx","map":"폴스타","matchType":"단판","memo":"단판","opponentName":"김윤중","opponentRace":"P","playedAt":"2026-03-15","playerName":"윤용태","playerRace":"P","playerUserId":"dbsdydx","result":"lose","standardDate":"2026-03-15","winnerName":"김윤중","winnerPlayer":"김윤중","winnerRace":"P","winnerSoopUserId":"","winnerUserId":""},{"date":"2026-02-21","elo":-7.4,"eloChange":-7.4,"id":"dbsdydx_2026-02-21_유영진_T_매치포인트_-7.4_3/2(2)_3/2선_2경기(2:0_유영진_승리)","isWin":false,"loseName":"윤용태","losePlayer":"윤용태","loseRace":"P","loseSoopUserId":"dbsdydx","loseUserId":"dbsdydx","loserSoopUserId":"dbsdydx","loserUserId":"dbsdydx","map":"매치포인트","matchType":"3/2(2)","memo":"3/2선 2경기(2:0 유영진 승리)","opponentName":"유영진","opponentRace":"T","playedAt":"2026-02-21","playerName":"윤용태","playerRace":"P","playerUserId":"dbsdydx","result":"lose","standardDate":"2026-02-21","winnerName":"유영진","winnerPlayer":"유영진","winnerRace":"T","winnerSoopUserId":"","winnerUserId":""},{"date":"2026-02-21","elo":-8,"eloChange":-8,"id":"dbsdydx_2026-02-21_유영진_T_네오_실피드_-8_3/2(1)_3/2선_1경기","isWin":false,"loseName":"윤용태","losePlayer":"윤용태","loseRace":"P","loseSoopUserId":"dbsdydx","loseUserId":"dbsdydx","loserSoopUserId":"dbsdydx","loserUserId":"dbsdydx","map":"네오 실피드","matchType":"3/2(1)","memo":"3/2선 1경기","opponentName":"유영진","opponentRace":"T","playedAt":"2026-02-21","playerName":"윤용태","playerRace":"P","playerUserId":"dbsdydx","result":"lose","standardDate":"2026-02-21","winnerName":"유영진","winnerPlayer":"유영진","winnerRace":"T","winnerSoopUserId":"","winnerUserId":""},{"date":"2026-02-06","elo":-7.8,"eloChange":-7.8,"id":"dbsdydx_2026-02-06_김성대_Z_폴스타_-7.8_단판_E-SCORE_TOURNAMENT_S1_7주차_32강","isWin":false,"loseName":"윤용태","losePlayer":"윤용태","loseRace":"P","loseSoopUserId":"dbsdydx","loseUserId":"dbsdydx","loserSoopUserId":"dbsdydx","loserUserId":"dbsdydx","map":"폴스타","matchType":"단판","memo":"E-SCORE TOURNAMENT S1 7주차 32강","opponentName":"김성대","opponentRace":"Z","playedAt":"2026-02-06","playerName":"윤용태","playerRace":"P","playerUserId":"dbsdydx","result":"lose","standardDate":"2026-02-06","winnerName":"김성대","winnerPlayer":"김성대","winnerRace":"Z","winnerSoopUserId":"","winnerUserId":""},{"date":"2026-02-04","elo":-19.1,"eloChange":-19.1,"id":"dbsdydx_2026-02-04_지동원_T_네오_실피드_-19.1_단판_씨나인vs츠캄몬스타즈_킹잭CK_2세트_위너스_6경기","isWin":false,"loseName":"윤용태","losePlayer":"윤용태","loseRace":"P","loseSoopUserId":"dbsdydx","loseUserId":"dbsdydx","loserSoopUserId":"dbsdydx","loserUserId":"dbsdydx","map":"네오 실피드","matchType":"단판","memo":"씨나인vs츠캄몬스타즈 킹잭CK 2세트 위너스 6경기","opponentName":"지동원","opponentRace":"T","playedAt":"2026-02-04","playerName":"윤용태","playerRace":"P","playerUserId":"dbsdydx","result":"lose","standardDate":"2026-02-04","winnerName":"지동원","winnerPlayer":"지동원","winnerRace":"T","winnerSoopUserId":"","winnerUserId":""},{"date":"2026-02-03","elo":-14.3,"eloChange":-14.3,"id":"dbsdydx_2026-02-03_박준오_Z_녹아웃_-14.3_단판_씨나인vs츠캄몬스타즈_킹잭CK_1세트_3경기","isWin":false,"loseName":"윤용태","losePlayer":"윤용태","loseRace":"P","loseSoopUserId":"dbsdydx","loseUserId":"dbsdydx","loserSoopUserId":"dbsdydx","loserUserId":"dbsdydx","map":"녹아웃","matchType":"단판","memo":"씨나인vs츠캄몬스타즈 킹잭CK 1세트 3경기","opponentName":"박준오","opponentRace":"Z","playedAt":"2026-02-03","playerName":"윤용태","playerRace":"P","playerUserId":"dbsdydx","result":"lose","standardDate":"2026-02-03","winnerName":"박준오","winnerPlayer":"박준오","winnerRace":"Z","winnerSoopUserId":"","winnerUserId":""},{"date":"2026-01-31","elo":-10,"eloChange":-10,"id":"dbsdydx_2026-01-31_이제동_Z_폴스타_-10_3/2(2)_2","isWin":false,"loseName":"윤용태","losePlayer":"윤용태","loseRace":"P","loseSoopUserId":"dbsdydx","loseUserId":"dbsdydx","loserSoopUserId":"dbsdydx","loserUserId":"dbsdydx","map":"폴스타","matchType":"3/2(2)","memo":"2","opponentName":"이제동","opponentRace":"Z","playedAt":"2026-01-31","playerName":"윤용태","playerRace":"P","playerUserId":"dbsdydx","result":"lose","standardDate":"2026-01-31","winnerName":"이제동","winnerPlayer":"이제동","winnerRace":"Z","winnerSoopUserId":"","winnerUserId":""},{"date":"2026-01-31","elo":-10.9,"eloChange":-10.9,"id":"dbsdydx_2026-01-31_이제동_Z_네오_실피드_-10.9_3/2(1)_1","isWin":false,"loseName":"윤용태","losePlayer":"윤용태","loseRace":"P","loseSoopUserId":"dbsdydx","loseUserId":"dbsdydx","loserSoopUserId":"dbsdydx","loserUserId":"dbsdydx","map":"네오 실피드","matchType":"3/2(1)","memo":"1","opponentName":"이제동","opponentRace":"Z","playedAt":"2026-01-31","playerName":"윤용태","playerRace":"P","playerUserId":"dbsdydx","result":"lose","standardDate":"2026-01-31","winnerName":"이제동","winnerPlayer":"이제동","winnerRace":"Z","winnerSoopUserId":"","winnerUserId":""},{"date":"2026-01-31","elo":11.1,"eloChange":11.1,"id":"dbsdydx_2026-01-31_김경모_Z_녹아웃_11.1_단판_케이대_저그반_점검_1경기","isWin":true,"loseName":"김경모","losePlayer":"김경모","loseRace":"Z","loseSoopUserId":"","loseUserId":"","loserSoopUserId":"","loserUserId":"","map":"녹아웃","matchType":"단판","memo":"케이대 저그반 점검 1경기","opponentName":"김경모","opponentRace":"Z","playedAt":"2026-01-31","playerName":"윤용태","playerRace":"P","playerUserId":"dbsdydx","result":"win","standardDate":"2026-01-31","winnerName":"윤용태","winnerPlayer":"윤용태","winnerRace":"P","winnerSoopUserId":"dbsdydx","winnerUserId":"dbsdydx"},{"date":"2026-01-30","elo":20.3,"eloChange":20.3,"id":"dbsdydx_2026-01-30_송병구_P_매치포인트_20.3_3/2(2)_3/2","isWin":true,"loseName":"송병구","losePlayer":"송병구","loseRace":"P","loseSoopUserId":"","loseUserId":"","loserSoopUserId":"","loserUserId":"","map":"매치포인트","matchType":"3/2(2)","memo":"3/2","opponentName":"송병구","opponentRace":"P","playedAt":"2026-01-30","playerName":"윤용태","playerRace":"P","playerUserId":"dbsdydx","result":"win","standardDate":"2026-01-30","winnerName":"윤용태","winnerPlayer":"윤용태","winnerRace":"P","winnerSoopUserId":"dbsdydx","winnerUserId":"dbsdydx"},{"date":"2026-01-30","elo":22.1,"eloChange":22.1,"id":"dbsdydx_2026-01-30_송병구_P_네오_실피드_22.1_3/2(1)_3/2","isWin":true,"loseName":"송병구","losePlayer":"송병구","loseRace":"P","loseSoopUserId":"","loseUserId":"","loserSoopUserId":"","loserUserId":"","map":"네오 실피드","matchType":"3/2(1)","memo":"3/2","opponentName":"송병구","opponentRace":"P","playedAt":"2026-01-30","playerName":"윤용태","playerRace":"P","playerUserId":"dbsdydx","result":"win","standardDate":"2026-01-30","winnerName":"윤용태","winnerPlayer":"윤용태","winnerRace":"P","winnerSoopUserId":"dbsdydx","winnerUserId":"dbsdydx"},{"date":"2026-01-30","elo":-8.7,"eloChange":-8.7,"id":"dbsdydx_2026-01-30_박상현_Z_폴스타_-8.7_단판_E-SCORE_TOURNAMENT_S1_6주차_32강","isWin":false,"loseName":"윤용태","losePlayer":"윤용태","loseRace":"P","loseSoopUserId":"dbsdydx","loseUserId":"dbsdydx","loserSoopUserId":"dbsdydx","loserUserId":"dbsdydx","map":"폴스타","matchType":"단판","memo":"E-SCORE TOURNAMENT S1 6주차 32강","opponentName":"박상현","opponentRace":"Z","playedAt":"2026-01-30","playerName":"윤용태","playerRace":"P","playerUserId":"dbsdydx","result":"lose","standardDate":"2026-01-30","winnerName":"박상현","winnerPlayer":"박상현","winnerRace":"Z","winnerSoopUserId":"","winnerUserId":""},{"date":"2026-01-28","elo":15.7,"eloChange":15.7,"id":"dbsdydx_2026-01-28_김윤중_P_도미네이터_15.7_11/6(6)_씨나인_시빌워_6SET","isWin":true,"loseName":"김윤중","losePlayer":"김윤중","loseRace":"P","loseSoopUserId":"","loseUserId":"","loserSoopUserId":"","loserUserId":"","map":"도미네이터","matchType":"11/6(6)","memo":"씨나인 시빌워 6SET","opponentName":"김윤중","opponentRace":"P","playedAt":"2026-01-28","playerName":"윤용태","playerRace":"P","playerUserId":"dbsdydx","result":"win","standardDate":"2026-01-28","winnerName":"윤용태","winnerPlayer":"윤용태","winnerRace":"P","winnerSoopUserId":"dbsdydx","winnerUserId":"dbsdydx"},{"date":"2026-01-23","elo":-7.2,"eloChange":-7.2,"id":"dbsdydx_2026-01-23_이제동_Z_폴스타_-7.2_단판_단판_이제동_승","isWin":false,"loseName":"윤용태","losePlayer":"윤용태","loseRace":"P","loseSoopUserId":"dbsdydx","loseUserId":"dbsdydx","loserSoopUserId":"dbsdydx","loserUserId":"dbsdydx","map":"폴스타","matchType":"단판","memo":"단판 이제동 승","opponentName":"이제동","opponentRace":"Z","playedAt":"2026-01-23","playerName":"윤용태","playerRace":"P","playerUserId":"dbsdydx","result":"lose","standardDate":"2026-01-23","winnerName":"이제동","winnerPlayer":"이제동","winnerRace":"Z","winnerSoopUserId":"","winnerUserId":""},{"date":"2026-01-23","elo":-7.8,"eloChange":-7.8,"id":"dbsdydx_2026-01-23_이제동_Z_녹아웃_-7.8_단판_단판","isWin":false,"loseName":"윤용태","losePlayer":"윤용태","loseRace":"P","loseSoopUserId":"dbsdydx","loseUserId":"dbsdydx","loserSoopUserId":"dbsdydx","loserUserId":"dbsdydx","map":"녹아웃","matchType":"단판","memo":"단판","opponentName":"이제동","opponentRace":"Z","playedAt":"2026-01-23","playerName":"윤용태","playerRace":"P","playerUserId":"dbsdydx","result":"lose","standardDate":"2026-01-23","winnerName":"이제동","winnerPlayer":"이제동","winnerRace":"Z","winnerSoopUserId":"","winnerUserId":""},{"date":"2026-01-18","elo":16.1,"eloChange":16.1,"id":"dbsdydx_2026-01-18_방태수_Z_라데온_16.1_단판_준메이저_프로리그_2세트_5경기","isWin":true,"loseName":"방태수","losePlayer":"방태수","loseRace":"Z","loseSoopUserId":"","loseUserId":"","loserSoopUserId":"","loserUserId":"","map":"라데온","matchType":"단판","memo":"준메이저 프로리그 2세트 5경기","opponentName":"방태수","opponentRace":"Z","playedAt":"2026-01-18","playerName":"윤용태","playerRace":"P","playerUserId":"dbsdydx","result":"win","standardDate":"2026-01-18","winnerName":"윤용태","winnerPlayer":"윤용태","winnerRace":"P","winnerSoopUserId":"dbsdydx","winnerUserId":"dbsdydx"},{"date":"2026-01-17","elo":18.4,"eloChange":18.4,"id":"dbsdydx_2026-01-17_방태수_Z_리트머스_18.4_단판_준메이저_프로리그_1세트_6경기","isWin":true,"loseName":"방태수","losePlayer":"방태수","loseRace":"Z","loseSoopUserId":"","loseUserId":"","loserSoopUserId":"","loserUserId":"","map":"리트머스","matchType":"단판","memo":"준메이저 프로리그 1세트 6경기","opponentName":"방태수","opponentRace":"Z","playedAt":"2026-01-17","playerName":"윤용태","playerRace":"P","playerUserId":"dbsdydx","result":"win","standardDate":"2026-01-17","winnerName":"윤용태","winnerPlayer":"윤용태","winnerRace":"P","winnerSoopUserId":"dbsdydx","winnerUserId":"dbsdydx"},{"date":"2026-01-17","elo":-15,"eloChange":-15,"id":"dbsdydx_2026-01-17_방태수_Z_녹아웃_-15_단판_준메이저_프로리그_1세트_5경기","isWin":false,"loseName":"윤용태","losePlayer":"윤용태","loseRace":"P","loseSoopUserId":"dbsdydx","loseUserId":"dbsdydx","loserSoopUserId":"dbsdydx","loserUserId":"dbsdydx","map":"녹아웃","matchType":"단판","memo":"준메이저 프로리그 1세트 5경기","opponentName":"방태수","opponentRace":"Z","playedAt":"2026-01-17","playerName":"윤용태","playerRace":"P","playerUserId":"dbsdydx","result":"lose","standardDate":"2026-01-17","winnerName":"방태수","winnerPlayer":"방태수","winnerRace":"Z","winnerSoopUserId":"","winnerUserId":""},{"date":"2025-12-20","elo":16.3,"eloChange":16.3,"id":"dbsdydx_2025-12-20_방태수_Z_메트로폴리스_16.3_9/5(4)_씨나인_스승vs제자_벌칙CK_4SET","isWin":true,"loseName":"방태수","losePlayer":"방태수","loseRace":"Z","loseSoopUserId":"","loseUserId":"","loserSoopUserId":"","loserUserId":"","map":"메트로폴리스","matchType":"9/5(4)","memo":"씨나인 스승vs제자 벌칙CK 4SET","opponentName":"방태수","opponentRace":"Z","playedAt":"2025-12-20","playerName":"윤용태","playerRace":"P","playerUserId":"dbsdydx","result":"win","standardDate":"2025-12-20","winnerName":"윤용태","winnerPlayer":"윤용태","winnerRace":"P","winnerSoopUserId":"dbsdydx","winnerUserId":"dbsdydx"},{"date":"2025-12-06","elo":18.8,"eloChange":18.8,"id":"dbsdydx_2025-12-06_김태영_T_라데온_18.8_단판_ㅅㅍ","isWin":true,"loseName":"김태영","losePlayer":"김태영","loseRace":"T","loseSoopUserId":"","loseUserId":"","loserSoopUserId":"","loserUserId":"","map":"라데온","matchType":"단판","memo":"ㅅㅍ","opponentName":"김태영","opponentRace":"T","playedAt":"2025-12-06","playerName":"윤용태","playerRace":"P","playerUserId":"dbsdydx","result":"win","standardDate":"2025-12-06","winnerName":"윤용태","winnerPlayer":"윤용태","winnerRace":"P","winnerSoopUserId":"dbsdydx","winnerUserId":"dbsdydx"},{"date":"2025-12-06","elo":-7,"eloChange":-7,"id":"dbsdydx_2025-12-06_임홍규_Z_폴스타_-7_3/2(3)_3/2선_3경기(2:1_임홍규_승리)","isWin":false,"loseName":"윤용태","losePlayer":"윤용태","loseRace":"P","loseSoopUserId":"dbsdydx","loseUserId":"dbsdydx","loserSoopUserId":"dbsdydx","loserUserId":"dbsdydx","map":"폴스타","matchType":"3/2(3)","memo":"3/2선 3경기(2:1 임홍규 승리)","opponentName":"임홍규","opponentRace":"Z","playedAt":"2025-12-06","playerName":"윤용태","playerRace":"P","playerUserId":"dbsdydx","result":"lose","standardDate":"2025-12-06","winnerName":"임홍규","winnerPlayer":"임홍규","winnerRace":"Z","winnerSoopUserId":"","winnerUserId":""},{"date":"2025-12-06","elo":-7.5,"eloChange":-7.5,"id":"dbsdydx_2025-12-06_임홍규_Z_도미네이터_-7.5_3/2(2)_3/2선_2경기","isWin":false,"loseName":"윤용태","losePlayer":"윤용태","loseRace":"P","loseSoopUserId":"dbsdydx","loseUserId":"dbsdydx","loserSoopUserId":"dbsdydx","loserUserId":"dbsdydx","map":"도미네이터","matchType":"3/2(2)","memo":"3/2선 2경기","opponentName":"임홍규","opponentRace":"Z","playedAt":"2025-12-06","playerName":"윤용태","playerRace":"P","playerUserId":"dbsdydx","result":"lose","standardDate":"2025-12-06","winnerName":"임홍규","winnerPlayer":"임홍규","winnerRace":"Z","winnerSoopUserId":"","winnerUserId":""},{"date":"2025-12-06","elo":26.1,"eloChange":26.1,"id":"dbsdydx_2025-12-06_임홍규_Z_라데온_26.1_3/2(1)_3/2선_1경기","isWin":true,"loseName":"임홍규","losePlayer":"임홍규","loseRace":"Z","loseSoopUserId":"","loseUserId":"","loserSoopUserId":"","loserUserId":"","map":"라데온","matchType":"3/2(1)","memo":"3/2선 1경기","opponentName":"임홍규","opponentRace":"Z","playedAt":"2025-12-06","playerName":"윤용태","playerRace":"P","playerUserId":"dbsdydx","result":"win","standardDate":"2025-12-06","winnerName":"윤용태","winnerPlayer":"윤용태","winnerRace":"P","winnerSoopUserId":"dbsdydx","winnerUserId":"dbsdydx"},{"date":"2025-12-06","elo":-12.9,"eloChange":-12.9,"id":"dbsdydx_2025-12-06_김태영_T_리트머스_-12.9_3/2(3)_32","isWin":false,"loseName":"윤용태","losePlayer":"윤용태","loseRace":"P","loseSoopUserId":"dbsdydx","loseUserId":"dbsdydx","loserSoopUserId":"dbsdydx","loserUserId":"dbsdydx","map":"리트머스","matchType":"3/2(3)","memo":"32","opponentName":"김태영","opponentRace":"T","playedAt":"2025-12-06","playerName":"윤용태","playerRace":"P","playerUserId":"dbsdydx","result":"lose","standardDate":"2025-12-06","winnerName":"김태영","winnerPlayer":"김태영","winnerRace":"T","winnerSoopUserId":"","winnerUserId":""},{"date":"2025-12-06","elo":-14.1,"eloChange":-14.1,"id":"dbsdydx_2025-12-06_김태영_T_라데온_-14.1_3/2(2)_32","isWin":false,"loseName":"윤용태","losePlayer":"윤용태","loseRace":"P","loseSoopUserId":"dbsdydx","loseUserId":"dbsdydx","loserSoopUserId":"dbsdydx","loserUserId":"dbsdydx","map":"라데온","matchType":"3/2(2)","memo":"32","opponentName":"김태영","opponentRace":"T","playedAt":"2025-12-06","playerName":"윤용태","playerRace":"P","playerUserId":"dbsdydx","result":"lose","standardDate":"2025-12-06","winnerName":"김태영","winnerPlayer":"김태영","winnerRace":"T","winnerSoopUserId":"","winnerUserId":""},{"date":"2025-12-06","elo":19.6,"eloChange":19.6,"id":"dbsdydx_2025-12-06_김태영_T_녹아웃_19.6_3/2(1)_32","isWin":true,"loseName":"김태영","losePlayer":"김태영","loseRace":"T","loseSoopUserId":"","loseUserId":"","loserSoopUserId":"","loserUserId":"","map":"녹아웃","matchType":"3/2(1)","memo":"32","opponentName":"김태영","opponentRace":"T","playedAt":"2025-12-06","playerName":"윤용태","playerRace":"P","playerUserId":"dbsdydx","result":"win","standardDate":"2025-12-06","winnerName":"윤용태","winnerPlayer":"윤용태","winnerRace":"P","winnerSoopUserId":"dbsdydx","winnerUserId":"dbsdydx"}]